[
  {
    "stopID": "11",
    "stopQueryDate": "2021-06-13T09:24:00.676Z",
    "count": 3,
    "results": [
      {
        "Direction": "Inbound",
        "Destination": "The Point",
        "Time": "00:09:02",
        "AVLS": "00:09:42",
        "Tram": "3025",
        "Action": "a",
        "Msg Sent": "13/06/2021 10:23:58",
        "Msg Received": "13/06/2021 10:23:58",
        "Msg Processed": "13/06/2021 10:23:59",
        "XML ID": "4444",
        "Total Lag": "1.0338054",
        "Create Lag": "0.7525572",
        "Process Lag": "0.2812482"
      },
      {
        "Direction": "Outbound",
        "Destination": "Tallaght",
        "Time": "00:01:10",
        "AVLS": "00:01:50",
        "Tram": "4013",
        "Action": "a",
        "Msg Sent": "13/06/2021 10:23:58",
        "Msg Received": "13/06/2021 10:23:58",
        "Msg Processed": "13/06/2021 10:23:59",
        "XML ID": "4445",
        "Total Lag": "1.1588158",
        "Create Lag": "0.8150592",
        "Process Lag": "0.3437566"
      },
      {
        "Direction": "Outbound",
        "Destination": "Tallaght",
        "Time": "00:11:10",
        "AVLS": "00:11:50",
        "Tram": "4007",
        "Action": "a",
        "Msg Sent": "13/06/2021 10:23:58",
        "Msg Received": "13/06/2021 10:23:58",
        "Msg Processed": "13/06/2021 10:23:59",
        "XML ID": "4444",
        "Total Lag": "1.0650663",
        "Create Lag": "0.7525572",
        "Process Lag": "0.3125091"
      }
    ]
  },
  {
    "stopID": "8",
    "stopQueryDate": "2021-06-13T09:24:00.705Z",
    "count": 4,
    "results": [
      {
        "Direction": "Inbound",
        "Destination": "The Point",
        "Time": "00:04:44",
        "AVLS": "00:05:24",
        "Tram": "3025",
        "Action": "a",
        "Msg Sent": "13/06/2021 10:23:58",
        "Msg Received": "13/06/2021 10:23:58",
        "Msg Processed": "13/06/2021 10:23:59",
        "XML ID": "4444",
        "Total Lag": "1.0181878",
        "Create Lag": "0.7525572",
        "Process Lag": "0.2656306"
      },
      {
        "Direction": "Inbound",
        "Destination": "The Point",
        "Time": "00:19:07",
        "AVLS": "00:19:47",
        "Tram": "3008",
        "Action": "a",
        "Msg Sent": "13/06/2021 10:23:58",
        "Msg Received": "13/06/2021 10:23:58",
        "Msg Processed": "13/06/2021 10:23:58",
        "XML ID": "4444",
        "Total Lag": "0.8931792",
        "Create Lag": "0.7525572",
        "Process Lag": "0.140622"
      },
      {
        "Direction": "Outbound",
        "Destination": "Tallaght",
        "Time": "00:05:23",
        "AVLS": "00:06:03",
        "Tram": "4013",
        "Action": "a",
        "Msg Sent": "13/06/2021 10:23:58",
        "Msg Received": "13/06/2021 10:23:58",
        "Msg Processed": "13/06/2021 10:23:59",
        "XML ID": "4445",
        "Total Lag": "1.1744303",
        "Create Lag": "0.8150592",
        "Process Lag": "0.3593711"
      },
      {
        "Direction": "Outbound",
        "Destination": "Tallaght",
        "Time": "00:15:23",
        "AVLS": "00:16:03",
        "Tram": "4007",
        "Action": "a",
        "Msg Sent": "13/06/2021 10:23:58",
        "Msg Received": "13/06/2021 10:23:58",
        "Msg Processed": "13/06/2021 10:23:59",
        "XML ID": "4445",
        "Total Lag": "1.0806815",
        "Create Lag": "0.8150592",
        "Process Lag": "0.2656223"
      }
    ]
  },
  {
    "stopID": "13",
    "stopQueryDate": "2021-06-13T09:24:00.715Z",
    "count": 3,
    "results": [
      {
        "Direction": "Inbound",
        "Destination": "The Point",
        "Time": "00:00:00",
        "AVLS": "00:00:19",
        "Tram": "3015",
        "Action": "a",
        "Msg Sent": "13/06/2021 10:23:58",
        "Msg Received": "13/06/2021 10:23:58",
        "Msg Processed": "13/06/2021 10:23:58",
        "XML ID": "4444",
        "Total Lag": "0.9400619",
        "Create Lag": "0.7525572",
        "Process Lag": "0.1875047"
      },
      {
        "Direction": "Inbound",
        "Destination": "The Point",
        "Time": "00:11:42",
        "AVLS": "00:12:22",
        "Tram": "3025",
        "Action": "a",
        "Msg Sent": "13/06/2021 10:23:58",
        "Msg Received": "13/06/2021 10:23:58",
        "Msg Processed": "13/06/2021 10:23:59",
        "XML ID": "4444",
        "Total Lag": "1.0338054",
        "Create Lag": "0.7525572",
        "Process Lag": "0.2812482"
      },
      {
        "Direction": "Outbound",
        "Destination": "Tallaght",
        "Time": "00:08:34",
        "AVLS": "00:09:14",
        "Tram": "4007",
        "Action": "a",
        "Msg Sent": "13/06/2021 10:23:58",
        "Msg Received": "13/06/2021 10:23:58",
        "Msg Processed": "13/06/2021 10:23:59",
        "XML ID": "4444",
        "Total Lag": "1.0650663",
        "Create Lag": "0.7525572",
        "Process Lag": "0.3125091"
      }
    ]
  },
  {
    "stopID": "15",
    "stopQueryDate": "2021-06-13T09:24:00.735Z",
    "count": 3,
    "results": [
      {
        "Direction": "Inbound",
        "Destination": "The Point",
        "Time": "00:02:19",
        "AVLS": "00:02:59",
        "Tram": "3015",
        "Action": "a",
        "Msg Sent": "13/06/2021 10:23:58",
        "Msg Received": "13/06/2021 10:23:58",
        "Msg Processed": "13/06/2021 10:23:58",
        "XML ID": "4444",
        "Total Lag": "0.9400619",
        "Create Lag": "0.7525572",
        "Process Lag": "0.1875047"
      },
      {
        "Direction": "Inbound",
        "Destination": "The Point",
        "Time": "00:14:22",
        "AVLS": "00:15:02",
        "Tram": "3025",
        "Action": "a",
        "Msg Sent": "13/06/2021 10:23:58",
        "Msg Received": "13/06/2021 10:23:58",
        "Msg Processed": "13/06/2021 10:23:59",
        "XML ID": "4444",
        "Total Lag": "1.0338054",
        "Create Lag": "0.7525572",
        "Process Lag": "0.2812482"
      },
      {
        "Direction": "Outbound",
        "Destination": "Tallaght",
        "Time": "00:05:44",
        "AVLS": "00:06:24",
        "Tram": "4007",
        "Action": "a",
        "Msg Sent": "13/06/2021 10:23:58",
        "Msg Received": "13/06/2021 10:23:58",
        "Msg Processed": "13/06/2021 10:23:59",
        "XML ID": "4444",
        "Total Lag": "1.0494305",
        "Create Lag": "0.7525572",
        "Process Lag": "0.2968733"
      }
    ]
  },
  {
    "stopID": "7",
    "stopQueryDate": "2021-06-13T09:24:00.762Z",
    "count": 4,
    "results": [
      {
        "Direction": "Inbound",
        "Destination": "The Point",
        "Time": "00:03:13",
        "AVLS": "00:03:53",
        "Tram": "3025",
        "Action": "a",
        "Msg Sent": "13/06/2021 10:23:58",
        "Msg Received": "13/06/2021 10:23:58",
        "Msg Processed": "13/06/2021 10:23:59",
        "XML ID": "4444",
        "Total Lag": "1.0181878",
        "Create Lag": "0.7525572",
        "Process Lag": "0.2656306"
      },
      {
        "Direction": "Inbound",
        "Destination": "The Point",
        "Time": "00:17:36",
        "AVLS": "00:18:16",
        "Tram": "3008",
        "Action": "a",
        "Msg Sent": "13/06/2021 10:23:58",
        "Msg Received": "13/06/2021 10:23:58",
        "Msg Processed": "13/06/2021 10:23:58",
        "XML ID": "4444",
        "Total Lag": "0.8931792",
        "Create Lag": "0.7525572",
        "Process Lag": "0.140622"
      },
      {
        "Direction": "Outbound",
        "Destination": "Tallaght",
        "Time": "00:06:52",
        "AVLS": "00:07:32",
        "Tram": "4013",
        "Action": "a",
        "Msg Sent": "13/06/2021 10:23:58",
        "Msg Received": "13/06/2021 10:23:58",
        "Msg Processed": "13/06/2021 10:23:59",
        "XML ID": "4445",
        "Total Lag": "1.1744303",
        "Create Lag": "0.8150592",
        "Process Lag": "0.3593711"
      },
      {
        "Direction": "Outbound",
        "Destination": "Tallaght",
        "Time": "00:16:52",
        "AVLS": "00:17:32",
        "Tram": "4007",
        "Action": "a",
        "Msg Sent": "13/06/2021 10:23:58",
        "Msg Received": "13/06/2021 10:23:58",
        "Msg Processed": "13/06/2021 10:23:59",
        "XML ID": "4445",
        "Total Lag": "1.0806815",
        "Create Lag": "0.8150592",
        "Process Lag": "0.2656223"
      }
    ]
  },
  {
    "stopID": "10",
    "stopQueryDate": "2021-06-13T09:24:00.774Z",
    "count": 3,
    "results": [
      {
        "Direction": "Inbound",
        "Destination": "The Point",
        "Time": "00:08:07",
        "AVLS": "00:08:47",
        "Tram": "3025",
        "Action": "a",
        "Msg Sent": "13/06/2021 10:23:58",
        "Msg Received": "13/06/2021 10:23:58",
        "Msg Processed": "13/06/2021 10:23:59",
        "XML ID": "4444",
        "Total Lag": "1.0338054",
        "Create Lag": "0.7525572",
        "Process Lag": "0.2812482"
      },
      {
        "Direction": "Outbound",
        "Destination": "Tallaght",
        "Time": "00:02:03",
        "AVLS": "00:02:43",
        "Tram": "4013",
        "Action": "a",
        "Msg Sent": "13/06/2021 10:23:58",
        "Msg Received": "13/06/2021 10:23:58",
        "Msg Processed": "13/06/2021 10:23:59",
        "XML ID": "4445",
        "Total Lag": "1.1588158",
        "Create Lag": "0.8150592",
        "Process Lag": "0.3437566"
      },
      {
        "Direction": "Outbound",
        "Destination": "Tallaght",
        "Time": "00:12:03",
        "AVLS": "00:12:43",
        "Tram": "4007",
        "Action": "a",
        "Msg Sent": "13/06/2021 10:23:58",
        "Msg Received": "13/06/2021 10:23:58",
        "Msg Processed": "13/06/2021 10:23:59",
        "XML ID": "4445",
        "Total Lag": "1.0650663",
        "Create Lag": "0.8150592",
        "Process Lag": "0.2500071"
      }
    ]
  },
  {
    "stopID": "6",
    "stopQueryDate": "2021-06-13T09:24:00.791Z",
    "count": 3,
    "results": [
      {
        "Direction": "Inbound",
        "Destination": "The Point",
        "Time": "00:00:00",
        "AVLS": "00:00:00",
        "Tram": "3025",
        "Action": "a",
        "Msg Sent": "13/06/2021 10:23:37",
        "Msg Received": "13/06/2021 10:23:37",
        "Msg Processed": "13/06/2021 10:23:37",
        "XML ID": "4435",
        "Total Lag": "0.5305513",
        "Create Lag": "0.5305513",
        "Process Lag": "0"
      },
      {
        "Direction": "Inbound",
        "Destination": "The Point",
        "Time": "00:13:20",
        "AVLS": "00:14:00",
        "Tram": "3008",
        "Action": "a",
        "Msg Sent": "13/06/2021 10:23:58",
        "Msg Received": "13/06/2021 10:23:58",
        "Msg Processed": "13/06/2021 10:23:58",
        "XML ID": "4444",
        "Total Lag": "0.8775555",
        "Create Lag": "0.7525572",
        "Process Lag": "0.1249983"
      },
      {
        "Direction": "Outbound",
        "Destination": "Tallaght",
        "Time": "00:10:43",
        "AVLS": "00:11:23",
        "Tram": "4013",
        "Action": "a",
        "Msg Sent": "13/06/2021 10:23:58",
        "Msg Received": "13/06/2021 10:23:58",
        "Msg Processed": "13/06/2021 10:23:59",
        "XML ID": "4445",
        "Total Lag": "1.1900592",
        "Create Lag": "0.8150592",
        "Process Lag": "0.375"
      }
    ]
  },
  {
    "stopID": "9",
    "stopQueryDate": "2021-06-13T09:24:00.801Z",
    "count": 3,
    "results": [
      {
        "Direction": "Inbound",
        "Destination": "The Point",
        "Time": "00:06:53",
        "AVLS": "00:07:33",
        "Tram": "3025",
        "Action": "a",
        "Msg Sent": "13/06/2021 10:23:58",
        "Msg Received": "13/06/2021 10:23:58",
        "Msg Processed": "13/06/2021 10:23:59",
        "XML ID": "4444",
        "Total Lag": "1.0181878",
        "Create Lag": "0.7525572",
        "Process Lag": "0.2656306"
      },
      {
        "Direction": "Outbound",
        "Destination": "Tallaght",
        "Time": "00:03:15",
        "AVLS": "00:03:55",
        "Tram": "4013",
        "Action": "a",
        "Msg Sent": "13/06/2021 10:23:58",
        "Msg Received": "13/06/2021 10:23:58",
        "Msg Processed": "13/06/2021 10:23:59",
        "XML ID": "4445",
        "Total Lag": "1.1744303",
        "Create Lag": "0.8150592",
        "Process Lag": "0.3593711"
      },
      {
        "Direction": "Outbound",
        "Destination": "Tallaght",
        "Time": "00:13:15",
        "AVLS": "00:13:55",
        "Tram": "4007",
        "Action": "a",
        "Msg Sent": "13/06/2021 10:23:58",
        "Msg Received": "13/06/2021 10:23:58",
        "Msg Processed": "13/06/2021 10:23:59",
        "XML ID": "4445",
        "Total Lag": "1.0806815",
        "Create Lag": "0.8150592",
        "Process Lag": "0.2656223"
      }
    ]
  },
  {
    "stopID": "2",
    "stopQueryDate": "2021-06-13T09:24:00.823Z",
    "count": 4,
    "results": [
      {
        "Direction": "Inbound",
        "Destination": "The Point",
        "Time": "00:03:34",
        "AVLS": "00:04:14",
        "Tram": "3008",
        "Action": "a",
        "Msg Sent": "13/06/2021 10:23:58",
        "Msg Received": "13/06/2021 10:23:58",
        "Msg Processed": "13/06/2021 10:23:58",
        "XML ID": "4444",
        "Total Lag": "0.8775555",
        "Create Lag": "0.7525572",
        "Process Lag": "0.1249983"
      },
      {
        "Direction": "Inbound",
        "Destination": "The Point",
        "Time": "00:10:36",
        "AVLS": "00:11:16",
        "Tram": "3011",
        "Action": "a",
        "Msg Sent": "13/06/2021 10:23:58",
        "Msg Received": "13/06/2021 10:23:58",
        "Msg Processed": "13/06/2021 10:23:58",
        "XML ID": "4444",
        "Total Lag": "0.9244321",
        "Create Lag": "0.7525572",
        "Process Lag": "0.1718749"
      },
      {
        "Direction": "Outbound",
        "Destination": "Tallaght",
        "Time": "00:00:44",
        "AVLS": "00:01:24",
        "Tram": "3011",
        "Action": "a",
        "Msg Sent": "13/06/2021 10:23:58",
        "Msg Received": "13/06/2021 10:23:58",
        "Msg Processed": "13/06/2021 10:23:58",
        "XML ID": "4444",
        "Total Lag": "0.9088068",
        "Create Lag": "0.7525572",
        "Process Lag": "0.1562496"
      },
      {
        "Direction": "Outbound",
        "Destination": "Tallaght",
        "Time": "00:07:43",
        "AVLS": "00:08:23",
        "Tram": "4011",
        "Action": "a",
        "Msg Sent": "13/06/2021 10:23:58",
        "Msg Received": "13/06/2021 10:23:58",
        "Msg Processed": "13/06/2021 10:23:59",
        "XML ID": "4445",
        "Total Lag": "1.1119326",
        "Create Lag": "0.8150592",
        "Process Lag": "0.2968734"
      }
    ]
  },
  {
    "stopID": "3",
    "stopQueryDate": "2021-06-13T09:24:00.842Z",
    "count": 5,
    "results": [
      {
        "Direction": "Inbound",
        "Destination": "The Point",
        "Time": "00:05:15",
        "AVLS": "00:05:55",
        "Tram": "3008",
        "Action": "a",
        "Msg Sent": "13/06/2021 10:23:58",
        "Msg Received": "13/06/2021 10:23:58",
        "Msg Processed": "13/06/2021 10:23:58",
        "XML ID": "4444",
        "Total Lag": "0.8775555",
        "Create Lag": "0.7525572",
        "Process Lag": "0.1249983"
      },
      {
        "Direction": "Inbound",
        "Destination": "The Point",
        "Time": "00:12:17",
        "AVLS": "00:12:57",
        "Tram": "3011",
        "Action": "a",
        "Msg Sent": "13/06/2021 10:23:58",
        "Msg Received": "13/06/2021 10:23:58",
        "Msg Processed": "13/06/2021 10:23:58",
        "XML ID": "4444",
        "Total Lag": "0.9244321",
        "Create Lag": "0.7525572",
        "Process Lag": "0.1718749"
      },
      {
        "Direction": "Outbound",
        "Destination": "Tallaght",
        "Time": "00:00:00",
        "AVLS": "00:00:08",
        "Tram": "3011",
        "Action": "a",
        "Msg Sent": "13/06/2021 10:23:58",
        "Msg Received": "13/06/2021 10:23:58",
        "Msg Processed": "13/06/2021 10:23:58",
        "XML ID": "4444",
        "Total Lag": "0.9088068",
        "Create Lag": "0.7525572",
        "Process Lag": "0.1562496"
      },
      {
        "Direction": "Outbound",
        "Destination": "Tallaght",
        "Time": "00:06:08",
        "AVLS": "00:06:48",
        "Tram": "4011",
        "Action": "a",
        "Msg Sent": "13/06/2021 10:23:58",
        "Msg Received": "13/06/2021 10:23:58",
        "Msg Processed": "13/06/2021 10:23:59",
        "XML ID": "4445",
        "Total Lag": "1.1119326",
        "Create Lag": "0.8150592",
        "Process Lag": "0.2968734"
      },
      {
        "Direction": "Outbound",
        "Destination": "Tallaght",
        "Time": "00:18:02",
        "AVLS": "00:18:42",
        "Tram": "4013",
        "Action": "a",
        "Msg Sent": "13/06/2021 10:23:58",
        "Msg Received": "13/06/2021 10:23:58",
        "Msg Processed": "13/06/2021 10:23:59",
        "XML ID": "4445",
        "Total Lag": "1.1900592",
        "Create Lag": "0.8150592",
        "Process Lag": "0.375"
      }
    ]
  },
  {
    "stopID": "23",
    "stopQueryDate": "2021-06-13T09:24:00.861Z",
    "count": 0,
    "results": []
  },
  {
    "stopID": "5",
    "stopQueryDate": "2021-06-13T09:24:00.880Z",
    "count": 6,
    "results": [
      {
        "Direction": "Inbound",
        "Destination": "The Point",
        "Time": "00:10:13",
        "AVLS": "00:10:53",
        "Tram": "3008",
        "Action": "a",
        "Msg Sent": "13/06/2021 10:23:58",
        "Msg Received": "13/06/2021 10:23:58",
        "Msg Processed": "13/06/2021 10:23:58",
        "XML ID": "4444",
        "Total Lag": "0.8775555",
        "Create Lag": "0.7525572",
        "Process Lag": "0.1249983"
      },
      {
        "Direction": "Inbound",
        "Destination": "The Point",
        "Time": "00:17:15",
        "AVLS": "00:17:55",
        "Tram": "3011",
        "Action": "a",
        "Msg Sent": "13/06/2021 10:23:58",
        "Msg Received": "13/06/2021 10:23:58",
        "Msg Processed": "13/06/2021 10:23:58",
        "XML ID": "4444",
        "Total Lag": "0.9400619",
        "Create Lag": "0.7525572",
        "Process Lag": "0.1875047"
      },
      {
        "Direction": "Outbound",
        "Destination": "Tallaght",
        "Time": "00:02:04",
        "AVLS": "00:02:44",
        "Tram": "4011",
        "Action": "a",
        "Msg Sent": "13/06/2021 10:23:58",
        "Msg Received": "13/06/2021 10:23:58",
        "Msg Processed": "13/06/2021 10:23:59",
        "XML ID": "4445",
        "Total Lag": "1.0963068",
        "Create Lag": "0.8150592",
        "Process Lag": "0.2812476"
      },
      {
        "Direction": "Outbound",
        "Destination": "Saggart",
        "Time": "00:05:20",
        "AVLS": "00:06:00",
        "Tram": "3009",
        "Action": "d",
        "Msg Sent": "13/06/2021 10:23:58",
        "Msg Received": "13/06/2021 10:23:58",
        "Msg Processed": "13/06/2021 10:23:58",
        "XML ID": "4444",
        "Total Lag": "0.7872048",
        "Create Lag": "0.7525572",
        "Process Lag": "0.0346476"
      },
      {
        "Direction": "Outbound",
        "Destination": "Saggart",
        "Time": "00:05:20",
        "AVLS": "00:06:00",
        "Tram": "4004",
        "Action": "d",
        "Msg Sent": "13/06/2021 10:23:58",
        "Msg Received": "13/06/2021 10:23:58",
        "Msg Processed": "13/06/2021 10:23:58",
        "XML ID": "4444",
        "Total Lag": "0.8150592",
        "Create Lag": "0.7525572",
        "Process Lag": "0.062502"
      },
      {
        "Direction": "Outbound",
        "Destination": "Tallaght",
        "Time": "00:13:58",
        "AVLS": "00:14:38",
        "Tram": "4013",
        "Action": "a",
        "Msg Sent": "13/06/2021 10:23:58",
        "Msg Received": "13/06/2021 10:23:58",
        "Msg Processed": "13/06/2021 10:23:59",
        "XML ID": "4445",
        "Total Lag": "1.1900592",
        "Create Lag": "0.8150592",
        "Process Lag": "0.375"
      }
    ]
  },
  {
    "stopID": "14",
    "stopQueryDate": "2021-06-13T09:24:00.907Z",
    "count": 3,
    "results": [
      {
        "Direction": "Inbound",
        "Destination": "The Point",
        "Time": "00:00:35",
        "AVLS": "00:01:15",
        "Tram": "3015",
        "Action": "a",
        "Msg Sent": "13/06/2021 10:23:58",
        "Msg Received": "13/06/2021 10:23:58",
        "Msg Processed": "13/06/2021 10:23:58",
        "XML ID": "4444",
        "Total Lag": "0.9400619",
        "Create Lag": "0.7525572",
        "Process Lag": "0.1875047"
      },
      {
        "Direction": "Inbound",
        "Destination": "The Point",
        "Time": "00:12:38",
        "AVLS": "00:13:18",
        "Tram": "3025",
        "Action": "a",
        "Msg Sent": "13/06/2021 10:23:58",
        "Msg Received": "13/06/2021 10:23:58",
        "Msg Processed": "13/06/2021 10:23:59",
        "XML ID": "4444",
        "Total Lag": "1.0338054",
        "Create Lag": "0.7525572",
        "Process Lag": "0.2812482"
      },
      {
        "Direction": "Outbound",
        "Destination": "Tallaght",
        "Time": "00:07:37",
        "AVLS": "00:08:17",
        "Tram": "4007",
        "Action": "a",
        "Msg Sent": "13/06/2021 10:23:58",
        "Msg Received": "13/06/2021 10:23:58",
        "Msg Processed": "13/06/2021 10:23:59",
        "XML ID": "4444",
        "Total Lag": "1.0650663",
        "Create Lag": "0.7525572",
        "Process Lag": "0.3125091"
      }
    ]
  },
  {
    "stopID": "12",
    "stopQueryDate": "2021-06-13T09:24:00.917Z",
    "count": 3,
    "results": [
      {
        "Direction": "Inbound",
        "Destination": "The Point",
        "Time": "00:10:04",
        "AVLS": "00:10:44",
        "Tram": "3025",
        "Action": "a",
        "Msg Sent": "13/06/2021 10:23:58",
        "Msg Received": "13/06/2021 10:23:58",
        "Msg Processed": "13/06/2021 10:23:59",
        "XML ID": "4444",
        "Total Lag": "1.0338054",
        "Create Lag": "0.7525572",
        "Process Lag": "0.2812482"
      },
      {
        "Direction": "Outbound",
        "Destination": "Tallaght",
        "Time": "00:00:09",
        "AVLS": "00:00:49",
        "Tram": "4013",
        "Action": "a",
        "Msg Sent": "13/06/2021 10:23:58",
        "Msg Received": "13/06/2021 10:23:58",
        "Msg Processed": "13/06/2021 10:23:59",
        "XML ID": "4445",
        "Total Lag": "1.1588158",
        "Create Lag": "0.8150592",
        "Process Lag": "0.3437566"
      },
      {
        "Direction": "Outbound",
        "Destination": "Tallaght",
        "Time": "00:10:09",
        "AVLS": "00:10:49",
        "Tram": "4007",
        "Action": "a",
        "Msg Sent": "13/06/2021 10:23:58",
        "Msg Received": "13/06/2021 10:23:58",
        "Msg Processed": "13/06/2021 10:23:59",
        "XML ID": "4444",
        "Total Lag": "1.0650663",
        "Create Lag": "0.7525572",
        "Process Lag": "0.3125091"
      }
    ]
  },
  {
    "stopID": "17",
    "stopQueryDate": "2021-06-13T09:24:00.920Z",
    "count": 3,
    "results": [
      {
        "Direction": "Inbound",
        "Destination": "The Point",
        "Time": "00:07:18",
        "AVLS": "00:07:58",
        "Tram": "3015",
        "Action": "a",
        "Msg Sent": "13/06/2021 10:23:58",
        "Msg Received": "13/06/2021 10:23:58",
        "Msg Processed": "13/06/2021 10:23:58",
        "XML ID": "4444",
        "Total Lag": "0.9400619",
        "Create Lag": "0.7525572",
        "Process Lag": "0.1875047"
      },
      {
        "Direction": "Outbound",
        "Destination": "Tallaght",
        "Time": "00:00:44",
        "AVLS": "00:01:24",
        "Tram": "4007",
        "Action": "a",
        "Msg Sent": "13/06/2021 10:23:58",
        "Msg Received": "13/06/2021 10:23:58",
        "Msg Processed": "13/06/2021 10:23:59",
        "XML ID": "4444",
        "Total Lag": "1.0494305",
        "Create Lag": "0.7525572",
        "Process Lag": "0.2968733"
      },
      {
        "Direction": "Outbound",
        "Destination": "Tallaght",
        "Time": "00:15:03",
        "AVLS": "00:15:43",
        "Tram": "3005",
        "Action": "a",
        "Msg Sent": "13/06/2021 10:23:58",
        "Msg Received": "13/06/2021 10:23:58",
        "Msg Processed": "13/06/2021 10:23:58",
        "XML ID": "4444",
        "Total Lag": "0.8619307",
        "Create Lag": "0.7525572",
        "Process Lag": "0.1093735"
      }
    ]
  },
  {
    "stopID": "19",
    "stopQueryDate": "2021-06-13T09:24:00.937Z",
    "count": 3,
    "results": [
      {
        "Direction": "Inbound",
        "Destination": "The Point",
        "Time": "00:00:44",
        "AVLS": "00:01:24",
        "Tram": "4012",
        "Action": "a",
        "Msg Sent": "13/06/2021 10:23:58",
        "Msg Received": "13/06/2021 10:23:58",
        "Msg Processed": "13/06/2021 10:23:59",
        "XML ID": "4445",
        "Total Lag": "1.1276831",
        "Create Lag": "0.8150592",
        "Process Lag": "0.3126239"
      },
      {
        "Direction": "Inbound",
        "Destination": "The Point",
        "Time": "00:10:58",
        "AVLS": "00:11:38",
        "Tram": "3015",
        "Action": "a",
        "Msg Sent": "13/06/2021 10:23:58",
        "Msg Received": "13/06/2021 10:23:58",
        "Msg Processed": "13/06/2021 10:23:58",
        "XML ID": "4444",
        "Total Lag": "0.9556804",
        "Create Lag": "0.7525572",
        "Process Lag": "0.2031232"
      },
      {
        "Direction": "Outbound",
        "Destination": "Tallaght",
        "Time": "00:11:38",
        "AVLS": "00:12:18",
        "Tram": "3005",
        "Action": "a",
        "Msg Sent": "13/06/2021 10:23:58",
        "Msg Received": "13/06/2021 10:23:58",
        "Msg Processed": "13/06/2021 10:23:58",
        "XML ID": "4444",
        "Total Lag": "0.8619307",
        "Create Lag": "0.7525572",
        "Process Lag": "0.1093735"
      }
    ]
  },
  {
    "stopID": "26",
    "stopQueryDate": "2021-06-13T09:24:00.945Z",
    "count": 2,
    "results": [
      {
        "Direction": "Inbound",
        "Destination": "Broombridge",
        "Time": "00:12:01",
        "AVLS": "00:12:41",
        "Tram": "5024",
        "Action": "a",
        "Msg Sent": "13/06/2021 10:23:48",
        "Msg Received": "13/06/2021 10:23:48",
        "Msg Processed": "13/06/2021 10:23:49",
        "XML ID": "4441",
        "Total Lag": "1.3150639",
        "Create Lag": "0.7507327",
        "Process Lag": "0.5643312"
      },
      {
        "Direction": "Outbound",
        "Destination": "Bride's Glen",
        "Time": "00:14:28",
        "AVLS": "00:15:08",
        "Tram": "5004",
        "Action": "a",
        "Msg Sent": "13/06/2021 10:23:58",
        "Msg Received": "13/06/2021 10:23:58",
        "Msg Processed": "13/06/2021 10:23:59",
        "XML ID": "4445",
        "Total Lag": "1.2213151",
        "Create Lag": "0.8150592",
        "Process Lag": "0.4062559"
      }
    ]
  },
  {
    "stopID": "18",
    "stopQueryDate": "2021-06-13T09:24:00.949Z",
    "count": 3,
    "results": [
      {
        "Direction": "Inbound",
        "Destination": "The Point",
        "Time": "00:00:00",
        "AVLS": "00:00:00",
        "Tram": "4012",
        "Action": "a",
        "Msg Sent": "13/06/2021 10:23:58",
        "Msg Received": "13/06/2021 10:23:58",
        "Msg Processed": "13/06/2021 10:23:59",
        "XML ID": "4445",
        "Total Lag": "1.1276831",
        "Create Lag": "0.8150592",
        "Process Lag": "0.3126239"
      },
      {
        "Direction": "Inbound",
        "Destination": "The Point",
        "Time": "00:09:34",
        "AVLS": "00:10:14",
        "Tram": "3015",
        "Action": "a",
        "Msg Sent": "13/06/2021 10:23:58",
        "Msg Received": "13/06/2021 10:23:58",
        "Msg Processed": "13/06/2021 10:23:58",
        "XML ID": "4444",
        "Total Lag": "0.9556804",
        "Create Lag": "0.7525572",
        "Process Lag": "0.2031232"
      },
      {
        "Direction": "Outbound",
        "Destination": "Tallaght",
        "Time": "00:12:50",
        "AVLS": "00:13:30",
        "Tram": "3005",
        "Action": "a",
        "Msg Sent": "13/06/2021 10:23:58",
        "Msg Received": "13/06/2021 10:23:58",
        "Msg Processed": "13/06/2021 10:23:58",
        "XML ID": "4444",
        "Total Lag": "0.8619307",
        "Create Lag": "0.7525572",
        "Process Lag": "0.1093735"
      }
    ]
  },
  {
    "stopID": "25",
    "stopQueryDate": "2021-06-13T09:24:00.957Z",
    "count": 2,
    "results": [
      {
        "Direction": "Inbound",
        "Destination": "Broombridge",
        "Time": "00:14:11",
        "AVLS": "00:14:51",
        "Tram": "5024",
        "Action": "a",
        "Msg Sent": "13/06/2021 10:23:48",
        "Msg Received": "13/06/2021 10:23:48",
        "Msg Processed": "13/06/2021 10:23:49",
        "XML ID": "4441",
        "Total Lag": "1.3150639",
        "Create Lag": "0.7507327",
        "Process Lag": "0.5643312"
      },
      {
        "Direction": "Outbound",
        "Destination": "Bride's Glen",
        "Time": "00:11:48",
        "AVLS": "00:12:28",
        "Tram": "5004",
        "Action": "a",
        "Msg Sent": "13/06/2021 10:23:58",
        "Msg Received": "13/06/2021 10:23:58",
        "Msg Processed": "13/06/2021 10:23:59",
        "XML ID": "4445",
        "Total Lag": "1.2056815",
        "Create Lag": "0.8150592",
        "Process Lag": "0.3906223"
      }
    ]
  },
  {
    "stopID": "21",
    "stopQueryDate": "2021-06-13T09:24:00.966Z",
    "count": 4,
    "results": [
      {
        "Direction": "Inbound",
        "Destination": "The Point",
        "Time": "00:05:40",
        "AVLS": "00:06:20",
        "Tram": "4012",
        "Action": "a",
        "Msg Sent": "13/06/2021 10:23:58",
        "Msg Received": "13/06/2021 10:23:58",
        "Msg Processed": "13/06/2021 10:23:59",
        "XML ID": "4445",
        "Total Lag": "1.1276831",
        "Create Lag": "0.8150592",
        "Process Lag": "0.3126239"
      },
      {
        "Direction": "Inbound",
        "Destination": "The Point",
        "Time": "00:15:54",
        "AVLS": "00:16:34",
        "Tram": "3015",
        "Action": "a",
        "Msg Sent": "13/06/2021 10:23:58",
        "Msg Received": "13/06/2021 10:23:58",
        "Msg Processed": "13/06/2021 10:23:58",
        "XML ID": "4444",
        "Total Lag": "0.9556804",
        "Create Lag": "0.7525572",
        "Process Lag": "0.2031232"
      },
      {
        "Direction": "Outbound",
        "Destination": "Tallaght",
        "Time": "00:07:02",
        "AVLS": "00:07:42",
        "Tram": "3005",
        "Action": "a",
        "Msg Sent": "13/06/2021 10:23:58",
        "Msg Received": "13/06/2021 10:23:58",
        "Msg Processed": "13/06/2021 10:23:58",
        "XML ID": "4444",
        "Total Lag": "0.8463055",
        "Create Lag": "0.7525572",
        "Process Lag": "0.0937483"
      },
      {
        "Direction": "Outbound",
        "Destination": "Tallaght",
        "Time": "00:18:22",
        "AVLS": "00:19:02",
        "Tram": "3010",
        "Action": "a",
        "Msg Sent": "13/06/2021 10:23:58",
        "Msg Received": "13/06/2021 10:23:58",
        "Msg Processed": "13/06/2021 10:23:58",
        "XML ID": "4444",
        "Total Lag": "0.9088068",
        "Create Lag": "0.7525572",
        "Process Lag": "0.1562496"
      }
    ]
  },
  {
    "stopID": "20",
    "stopQueryDate": "2021-06-13T09:24:00.975Z",
    "count": 3,
    "results": [
      {
        "Direction": "Inbound",
        "Destination": "The Point",
        "Time": "00:02:54",
        "AVLS": "00:03:34",
        "Tram": "4012",
        "Action": "a",
        "Msg Sent": "13/06/2021 10:23:58",
        "Msg Received": "13/06/2021 10:23:58",
        "Msg Processed": "13/06/2021 10:23:59",
        "XML ID": "4445",
        "Total Lag": "1.1276831",
        "Create Lag": "0.8150592",
        "Process Lag": "0.3126239"
      },
      {
        "Direction": "Inbound",
        "Destination": "The Point",
        "Time": "00:13:08",
        "AVLS": "00:13:48",
        "Tram": "3015",
        "Action": "a",
        "Msg Sent": "13/06/2021 10:23:58",
        "Msg Received": "13/06/2021 10:23:58",
        "Msg Processed": "13/06/2021 10:23:58",
        "XML ID": "4444",
        "Total Lag": "0.9556804",
        "Create Lag": "0.7525572",
        "Process Lag": "0.2031232"
      },
      {
        "Direction": "Outbound",
        "Destination": "Tallaght",
        "Time": "00:09:29",
        "AVLS": "00:10:09",
        "Tram": "3005",
        "Action": "a",
        "Msg Sent": "13/06/2021 10:23:58",
        "Msg Received": "13/06/2021 10:23:58",
        "Msg Processed": "13/06/2021 10:23:58",
        "XML ID": "4444",
        "Total Lag": "0.8619307",
        "Create Lag": "0.7525572",
        "Process Lag": "0.1093735"
      }
    ]
  },
  {
    "stopID": "22",
    "stopQueryDate": "2021-06-13T09:24:00.986Z",
    "count": 4,
    "results": [
      {
        "Direction": "Inbound",
        "Destination": "The Point",
        "Time": "00:08:44",
        "AVLS": "00:09:24",
        "Tram": "4012",
        "Action": "a",
        "Msg Sent": "13/06/2021 10:23:58",
        "Msg Received": "13/06/2021 10:23:58",
        "Msg Processed": "13/06/2021 10:23:59",
        "XML ID": "4445",
        "Total Lag": "1.1431816",
        "Create Lag": "0.8150592",
        "Process Lag": "0.3281224"
      },
      {
        "Direction": "Inbound",
        "Destination": "The Point",
        "Time": "00:18:58",
        "AVLS": "00:19:38",
        "Tram": "3015",
        "Action": "a",
        "Msg Sent": "13/06/2021 10:23:58",
        "Msg Received": "13/06/2021 10:23:58",
        "Msg Processed": "13/06/2021 10:23:58",
        "XML ID": "4444",
        "Total Lag": "0.9713116",
        "Create Lag": "0.7525572",
        "Process Lag": "0.2187544"
      },
      {
        "Direction": "Outbound",
        "Destination": "Tallaght",
        "Time": "00:03:34",
        "AVLS": "00:04:14",
        "Tram": "3005",
        "Action": "a",
        "Msg Sent": "13/06/2021 10:23:58",
        "Msg Received": "13/06/2021 10:23:58",
        "Msg Processed": "13/06/2021 10:23:58",
        "XML ID": "4444",
        "Total Lag": "0.8463055",
        "Create Lag": "0.7525572",
        "Process Lag": "0.0937483"
      },
      {
        "Direction": "Outbound",
        "Destination": "Tallaght",
        "Time": "00:14:54",
        "AVLS": "00:15:34",
        "Tram": "3010",
        "Action": "a",
        "Msg Sent": "13/06/2021 10:23:58",
        "Msg Received": "13/06/2021 10:23:58",
        "Msg Processed": "13/06/2021 10:23:58",
        "XML ID": "4444",
        "Total Lag": "0.9088068",
        "Create Lag": "0.7525572",
        "Process Lag": "0.1562496"
      }
    ]
  },
  {
    "stopID": "16",
    "stopQueryDate": "2021-06-13T09:24:00.995Z",
    "count": 4,
    "results": [
      {
        "Direction": "Inbound",
        "Destination": "The Point",
        "Time": "00:04:54",
        "AVLS": "00:05:34",
        "Tram": "3015",
        "Action": "a",
        "Msg Sent": "13/06/2021 10:23:58",
        "Msg Received": "13/06/2021 10:23:58",
        "Msg Processed": "13/06/2021 10:23:58",
        "XML ID": "4444",
        "Total Lag": "0.9400619",
        "Create Lag": "0.7525572",
        "Process Lag": "0.1875047"
      },
      {
        "Direction": "Inbound",
        "Destination": "The Point",
        "Time": "00:16:57",
        "AVLS": "00:17:37",
        "Tram": "3025",
        "Action": "a",
        "Msg Sent": "13/06/2021 10:23:58",
        "Msg Received": "13/06/2021 10:23:58",
        "Msg Processed": "13/06/2021 10:23:59",
        "XML ID": "4444",
        "Total Lag": "1.0338054",
        "Create Lag": "0.7525572",
        "Process Lag": "0.2812482"
      },
      {
        "Direction": "Outbound",
        "Destination": "Tallaght",
        "Time": "00:02:43",
        "AVLS": "00:03:23",
        "Tram": "4007",
        "Action": "a",
        "Msg Sent": "13/06/2021 10:23:58",
        "Msg Received": "13/06/2021 10:23:58",
        "Msg Processed": "13/06/2021 10:23:59",
        "XML ID": "4444",
        "Total Lag": "1.0494305",
        "Create Lag": "0.7525572",
        "Process Lag": "0.2968733"
      },
      {
        "Direction": "Outbound",
        "Destination": "Tallaght",
        "Time": "00:17:02",
        "AVLS": "00:17:42",
        "Tram": "3005",
        "Action": "a",
        "Msg Sent": "13/06/2021 10:23:58",
        "Msg Received": "13/06/2021 10:23:58",
        "Msg Processed": "13/06/2021 10:23:58",
        "XML ID": "4444",
        "Total Lag": "0.8619307",
        "Create Lag": "0.7525572",
        "Process Lag": "0.1093735"
      }
    ]
  },
  {
    "stopID": "24",
    "stopQueryDate": "2021-06-13T09:24:01.004Z",
    "count": 3,
    "results": [
      {
        "Direction": "Inbound",
        "Destination": "Broombridge",
        "Time": "00:01:39",
        "AVLS": "00:02:19",
        "Tram": "5005",
        "Action": "a",
        "Msg Sent": "13/06/2021 10:23:58",
        "Msg Received": "13/06/2021 10:23:58",
        "Msg Processed": "13/06/2021 10:23:59",
        "XML ID": "4445",
        "Total Lag": "1.2213151",
        "Create Lag": "0.8150592",
        "Process Lag": "0.4062559"
      },
      {
        "Direction": "Inbound",
        "Destination": "Broombridge",
        "Time": "00:17:09",
        "AVLS": "00:17:49",
        "Tram": "5024",
        "Action": "a",
        "Msg Sent": "13/06/2021 10:23:48",
        "Msg Received": "13/06/2021 10:23:48",
        "Msg Processed": "13/06/2021 10:23:49",
        "XML ID": "4441",
        "Total Lag": "1.3150639",
        "Create Lag": "0.7507327",
        "Process Lag": "0.5643312"
      },
      {
        "Direction": "Outbound",
        "Destination": "Bride's Glen",
        "Time": "00:09:50",
        "AVLS": "00:10:30",
        "Tram": "5004",
        "Action": "a",
        "Msg Sent": "13/06/2021 10:23:58",
        "Msg Received": "13/06/2021 10:23:58",
        "Msg Processed": "13/06/2021 10:23:59",
        "XML ID": "4445",
        "Total Lag": "1.2056815",
        "Create Lag": "0.8150592",
        "Process Lag": "0.3906223"
      }
    ]
  },
  {
    "stopID": "28",
    "stopQueryDate": "2021-06-13T09:24:01.014Z",
    "count": 3,
    "results": [
      {
        "Direction": "Inbound",
        "Destination": "Broombridge",
        "Time": "00:09:09",
        "AVLS": "00:09:49",
        "Tram": "5024",
        "Action": "a",
        "Msg Sent": "13/06/2021 10:23:48",
        "Msg Received": "13/06/2021 10:23:48",
        "Msg Processed": "13/06/2021 10:23:49",
        "XML ID": "4441",
        "Total Lag": "1.3150639",
        "Create Lag": "0.7507327",
        "Process Lag": "0.5643312"
      },
      {
        "Direction": "Outbound",
        "Destination": "Bride's Glen",
        "Time": "00:01:29",
        "AVLS": "00:02:09",
        "Tram": "5018",
        "Action": "a",
        "Msg Sent": "13/06/2021 10:23:58",
        "Msg Received": "13/06/2021 10:23:58",
        "Msg Processed": "13/06/2021 10:23:59",
        "XML ID": "4445",
        "Total Lag": "1.3463073",
        "Create Lag": "0.8150592",
        "Process Lag": "0.5312481"
      },
      {
        "Direction": "Outbound",
        "Destination": "Bride's Glen",
        "Time": "00:17:50",
        "AVLS": "00:18:30",
        "Tram": "5004",
        "Action": "a",
        "Msg Sent": "13/06/2021 10:23:58",
        "Msg Received": "13/06/2021 10:23:58",
        "Msg Processed": "13/06/2021 10:23:59",
        "XML ID": "4445",
        "Total Lag": "1.2213151",
        "Create Lag": "0.8150592",
        "Process Lag": "0.4062559"
      }
    ]
  },
  {
    "stopID": "29",
    "stopQueryDate": "2021-06-13T09:24:01.033Z",
    "count": 3,
    "results": [
      {
        "Direction": "Inbound",
        "Destination": "Broombridge",
        "Time": "00:07:40",
        "AVLS": "00:08:20",
        "Tram": "5024",
        "Action": "a",
        "Msg Sent": "13/06/2021 10:23:48",
        "Msg Received": "13/06/2021 10:23:48",
        "Msg Processed": "13/06/2021 10:23:49",
        "XML ID": "4441",
        "Total Lag": "1.2994307",
        "Create Lag": "0.7507327",
        "Process Lag": "0.548698"
      },
      {
        "Direction": "Outbound",
        "Destination": "Bride's Glen",
        "Time": "00:02:57",
        "AVLS": "00:03:37",
        "Tram": "5018",
        "Action": "a",
        "Msg Sent": "13/06/2021 10:23:58",
        "Msg Received": "13/06/2021 10:23:58",
        "Msg Processed": "13/06/2021 10:23:59",
        "XML ID": "4445",
        "Total Lag": "1.3619476",
        "Create Lag": "0.8150592",
        "Process Lag": "0.5468884"
      },
      {
        "Direction": "Outbound",
        "Destination": "Bride's Glen",
        "Time": "00:19:18",
        "AVLS": "00:19:58",
        "Tram": "5004",
        "Action": "a",
        "Msg Sent": "13/06/2021 10:23:58",
        "Msg Received": "13/06/2021 10:23:58",
        "Msg Processed": "13/06/2021 10:23:59",
        "XML ID": "4445",
        "Total Lag": "1.2213151",
        "Create Lag": "0.8150592",
        "Process Lag": "0.4062559"
      }
    ]
  },
  {
    "stopID": "30",
    "stopQueryDate": "2021-06-13T09:24:01.042Z",
    "count": 3,
    "results": [
      {
        "Direction": "Inbound",
        "Destination": "Broombridge",
        "Time": "00:05:55",
        "AVLS": "00:06:35",
        "Tram": "5024",
        "Action": "a",
        "Msg Sent": "13/06/2021 10:23:48",
        "Msg Received": "13/06/2021 10:23:48",
        "Msg Processed": "13/06/2021 10:23:49",
        "XML ID": "4441",
        "Total Lag": "1.2994307",
        "Create Lag": "0.7507327",
        "Process Lag": "0.548698"
      },
      {
        "Direction": "Inbound",
        "Destination": "Broombridge",
        "Time": "00:18:51",
        "AVLS": "00:19:31",
        "Tram": "5019",
        "Action": "a",
        "Msg Sent": "13/06/2021 10:23:48",
        "Msg Received": "13/06/2021 10:23:48",
        "Msg Processed": "13/06/2021 10:23:49",
        "XML ID": "4441",
        "Total Lag": "1.2838075",
        "Create Lag": "0.7507327",
        "Process Lag": "0.5330748"
      },
      {
        "Direction": "Outbound",
        "Destination": "Bride's Glen",
        "Time": "00:04:43",
        "AVLS": "00:05:23",
        "Tram": "5018",
        "Action": "a",
        "Msg Sent": "13/06/2021 10:23:58",
        "Msg Received": "13/06/2021 10:23:58",
        "Msg Processed": "13/06/2021 10:23:59",
        "XML ID": "4445",
        "Total Lag": "1.3619476",
        "Create Lag": "0.8150592",
        "Process Lag": "0.5468884"
      }
    ]
  },
  {
    "stopID": "4",
    "stopQueryDate": "2021-06-13T09:24:01.060Z",
    "count": 9,
    "results": [
      {
        "Direction": "Inbound",
        "Destination": "The Point",
        "Time": "00:08:20",
        "AVLS": "00:09:00",
        "Tram": "3008",
        "Action": "a",
        "Msg Sent": "13/06/2021 10:23:58",
        "Msg Received": "13/06/2021 10:23:58",
        "Msg Processed": "13/06/2021 10:23:58",
        "XML ID": "4444",
        "Total Lag": "0.8775555",
        "Create Lag": "0.7525572",
        "Process Lag": "0.1249983"
      },
      {
        "Direction": "Inbound",
        "Destination": "The Point",
        "Time": "00:15:22",
        "AVLS": "00:16:02",
        "Tram": "3011",
        "Action": "a",
        "Msg Sent": "13/06/2021 10:23:58",
        "Msg Received": "13/06/2021 10:23:58",
        "Msg Processed": "13/06/2021 10:23:58",
        "XML ID": "4444",
        "Total Lag": "0.9244321",
        "Create Lag": "0.7525572",
        "Process Lag": "0.1718749"
      },
      {
        "Direction": "Outbound",
        "Destination": "Saggart",
        "Time": "00:00:00",
        "AVLS": "00:00:32",
        "Tram": "3002",
        "Action": "a",
        "Msg Sent": "13/06/2021 10:23:58",
        "Msg Received": "13/06/2021 10:23:58",
        "Msg Processed": "13/06/2021 10:23:58",
        "XML ID": "4444",
        "Total Lag": "0.8306834",
        "Create Lag": "0.7525572",
        "Process Lag": "0.0781262"
      },
      {
        "Direction": "Outbound",
        "Destination": "Tallaght",
        "Time": "00:03:49",
        "AVLS": "00:04:29",
        "Tram": "4011",
        "Action": "a",
        "Msg Sent": "13/06/2021 10:23:58",
        "Msg Received": "13/06/2021 10:23:58",
        "Msg Processed": "13/06/2021 10:23:59",
        "XML ID": "4445",
        "Total Lag": "1.1119326",
        "Create Lag": "0.8150592",
        "Process Lag": "0.2968734"
      },
      {
        "Direction": "Outbound",
        "Destination": "Saggart",
        "Time": "00:06:52",
        "AVLS": "00:07:32",
        "Tram": "3019",
        "Action": "a",
        "Msg Sent": "13/06/2021 10:23:58",
        "Msg Received": "13/06/2021 10:23:58",
        "Msg Processed": "13/06/2021 10:23:58",
        "XML ID": "4444",
        "Total Lag": "0.9713116",
        "Create Lag": "0.7525572",
        "Process Lag": "0.2187544"
      },
      {
        "Direction": "Outbound",
        "Destination": "Saggart",
        "Time": "00:07:03",
        "AVLS": "00:07:43",
        "Tram": "3009",
        "Action": "a",
        "Msg Sent": "13/06/2021 10:23:58",
        "Msg Received": "13/06/2021 10:23:58",
        "Msg Processed": "13/06/2021 10:23:58",
        "XML ID": "4444",
        "Total Lag": "0.7872048",
        "Create Lag": "0.7525572",
        "Process Lag": "0.0346476"
      },
      {
        "Direction": "Outbound",
        "Destination": "Saggart",
        "Time": "00:07:03",
        "AVLS": "00:07:43",
        "Tram": "4004",
        "Action": "a",
        "Msg Sent": "13/06/2021 10:23:58",
        "Msg Received": "13/06/2021 10:23:58",
        "Msg Processed": "13/06/2021 10:23:58",
        "XML ID": "4444",
        "Total Lag": "0.8150592",
        "Create Lag": "0.7525572",
        "Process Lag": "0.062502"
      },
      {
        "Direction": "Outbound",
        "Destination": "Tallaght",
        "Time": "00:15:43",
        "AVLS": "00:16:23",
        "Tram": "4013",
        "Action": "a",
        "Msg Sent": "13/06/2021 10:23:58",
        "Msg Received": "13/06/2021 10:23:58",
        "Msg Processed": "13/06/2021 10:23:59",
        "XML ID": "4445",
        "Total Lag": "1.1900592",
        "Create Lag": "0.8150592",
        "Process Lag": "0.375"
      },
      {
        "Direction": "Outbound",
        "Destination": "Saggart",
        "Time": "00:18:52",
        "AVLS": "00:19:32",
        "Tram": "3020",
        "Action": "a",
        "Msg Sent": "13/06/2021 10:23:58",
        "Msg Received": "13/06/2021 10:23:58",
        "Msg Processed": "13/06/2021 10:23:59",
        "XML ID": "4444",
        "Total Lag": "1.0181878",
        "Create Lag": "0.7525572",
        "Process Lag": "0.2656306"
      }
    ]
  },
  {
    "stopID": "32",
    "stopQueryDate": "2021-06-13T09:24:01.156Z",
    "count": 3,
    "results": [
      {
        "Direction": "Inbound",
        "Destination": "Broombridge",
        "Time": "00:02:09",
        "AVLS": "00:02:49",
        "Tram": "5024",
        "Action": "a",
        "Msg Sent": "13/06/2021 10:23:48",
        "Msg Received": "13/06/2021 10:23:48",
        "Msg Processed": "13/06/2021 10:23:49",
        "XML ID": "4441",
        "Total Lag": "1.2994307",
        "Create Lag": "0.7507327",
        "Process Lag": "0.548698"
      },
      {
        "Direction": "Inbound",
        "Destination": "Broombridge",
        "Time": "00:14:55",
        "AVLS": "00:15:35",
        "Tram": "5019",
        "Action": "a",
        "Msg Sent": "13/06/2021 10:23:58",
        "Msg Received": "13/06/2021 10:23:58",
        "Msg Processed": "13/06/2021 10:23:59",
        "XML ID": "4445",
        "Total Lag": "1.4088067",
        "Create Lag": "0.8150592",
        "Process Lag": "0.5937475"
      },
      {
        "Direction": "Outbound",
        "Destination": "Bride's Glen",
        "Time": "00:08:29",
        "AVLS": "00:09:09",
        "Tram": "5018",
        "Action": "a",
        "Msg Sent": "13/06/2021 10:23:58",
        "Msg Received": "13/06/2021 10:23:58",
        "Msg Processed": "13/06/2021 10:23:59",
        "XML ID": "4445",
        "Total Lag": "1.3619476",
        "Create Lag": "0.8150592",
        "Process Lag": "0.5468884"
      }
    ]
  },
  {
    "stopID": "35",
    "stopQueryDate": "2021-06-13T09:24:01.174Z",
    "count": 3,
    "results": [
      {
        "Direction": "Inbound",
        "Destination": "Broombridge",
        "Time": "00:09:30",
        "AVLS": "00:10:10",
        "Tram": "5019",
        "Action": "a",
        "Msg Sent": "13/06/2021 10:23:58",
        "Msg Received": "13/06/2021 10:23:58",
        "Msg Processed": "13/06/2021 10:23:59",
        "XML ID": "4445",
        "Total Lag": "1.3931807",
        "Create Lag": "0.8150592",
        "Process Lag": "0.5781215"
      },
      {
        "Direction": "Outbound",
        "Destination": "Bride's Glen",
        "Time": "00:00:00",
        "AVLS": "00:00:00",
        "Tram": "5010",
        "Action": "a",
        "Msg Sent": "13/06/2021 10:23:58",
        "Msg Received": "13/06/2021 10:23:58",
        "Msg Processed": "13/06/2021 10:23:59",
        "XML ID": "4445",
        "Total Lag": "1.2525606",
        "Create Lag": "0.8150592",
        "Process Lag": "0.4375014"
      },
      {
        "Direction": "Outbound",
        "Destination": "Bride's Glen",
        "Time": "00:13:08",
        "AVLS": "00:13:48",
        "Tram": "5018",
        "Action": "a",
        "Msg Sent": "13/06/2021 10:23:58",
        "Msg Received": "13/06/2021 10:23:58",
        "Msg Processed": "13/06/2021 10:23:59",
        "XML ID": "4445",
        "Total Lag": "1.377561",
        "Create Lag": "0.8150592",
        "Process Lag": "0.5625018"
      }
    ]
  },
  {
    "stopID": "34",
    "stopQueryDate": "2021-06-13T09:24:01.178Z",
    "count": 2,
    "results": [
      {
        "Direction": "Inbound",
        "Destination": "Broombridge",
        "Time": "00:11:30",
        "AVLS": "00:12:10",
        "Tram": "5019",
        "Action": "a",
        "Msg Sent": "13/06/2021 10:23:58",
        "Msg Received": "13/06/2021 10:23:58",
        "Msg Processed": "13/06/2021 10:23:59",
        "XML ID": "4445",
        "Total Lag": "1.4088067",
        "Create Lag": "0.8150592",
        "Process Lag": "0.5937475"
      },
      {
        "Direction": "Outbound",
        "Destination": "Bride's Glen",
        "Time": "00:11:29",
        "AVLS": "00:12:09",
        "Tram": "5018",
        "Action": "a",
        "Msg Sent": "13/06/2021 10:23:58",
        "Msg Received": "13/06/2021 10:23:58",
        "Msg Processed": "13/06/2021 10:23:59",
        "XML ID": "4445",
        "Total Lag": "1.377561",
        "Create Lag": "0.8150592",
        "Process Lag": "0.5625018"
      }
    ]
  },
  {
    "stopID": "36",
    "stopQueryDate": "2021-06-13T09:24:01.194Z",
    "count": 3,
    "results": [
      {
        "Direction": "Inbound",
        "Destination": "Broombridge",
        "Time": "00:07:55",
        "AVLS": "00:08:35",
        "Tram": "5019",
        "Action": "a",
        "Msg Sent": "13/06/2021 10:23:58",
        "Msg Received": "13/06/2021 10:23:58",
        "Msg Processed": "13/06/2021 10:23:59",
        "XML ID": "4445",
        "Total Lag": "1.3931807",
        "Create Lag": "0.8150592",
        "Process Lag": "0.5781215"
      },
      {
        "Direction": "Outbound",
        "Destination": "Bride's Glen",
        "Time": "00:00:41",
        "AVLS": "00:01:21",
        "Tram": "5010",
        "Action": "a",
        "Msg Sent": "13/06/2021 10:23:58",
        "Msg Received": "13/06/2021 10:23:58",
        "Msg Processed": "13/06/2021 10:23:59",
        "XML ID": "4445",
        "Total Lag": "1.2525606",
        "Create Lag": "0.8150592",
        "Process Lag": "0.4375014"
      },
      {
        "Direction": "Outbound",
        "Destination": "Bride's Glen",
        "Time": "00:14:29",
        "AVLS": "00:15:09",
        "Tram": "5018",
        "Action": "a",
        "Msg Sent": "13/06/2021 10:23:58",
        "Msg Received": "13/06/2021 10:23:58",
        "Msg Processed": "13/06/2021 10:23:59",
        "XML ID": "4445",
        "Total Lag": "1.377561",
        "Create Lag": "0.8150592",
        "Process Lag": "0.5625018"
      }
    ]
  },
  {
    "stopID": "33",
    "stopQueryDate": "2021-06-13T09:24:01.222Z",
    "count": 3,
    "results": [
      {
        "Direction": "Inbound",
        "Destination": "Broombridge",
        "Time": "00:00:27",
        "AVLS": "00:01:07",
        "Tram": "5024",
        "Action": "a",
        "Msg Sent": "13/06/2021 10:23:48",
        "Msg Received": "13/06/2021 10:23:48",
        "Msg Processed": "13/06/2021 10:23:49",
        "XML ID": "4441",
        "Total Lag": "1.2994307",
        "Create Lag": "0.7507327",
        "Process Lag": "0.548698"
      },
      {
        "Direction": "Inbound",
        "Destination": "Broombridge",
        "Time": "00:13:13",
        "AVLS": "00:13:53",
        "Tram": "5019",
        "Action": "a",
        "Msg Sent": "13/06/2021 10:23:58",
        "Msg Received": "13/06/2021 10:23:58",
        "Msg Processed": "13/06/2021 10:23:59",
        "XML ID": "4445",
        "Total Lag": "1.4088067",
        "Create Lag": "0.8150592",
        "Process Lag": "0.5937475"
      },
      {
        "Direction": "Outbound",
        "Destination": "Bride's Glen",
        "Time": "00:09:55",
        "AVLS": "00:10:35",
        "Tram": "5018",
        "Action": "a",
        "Msg Sent": "13/06/2021 10:23:58",
        "Msg Received": "13/06/2021 10:23:58",
        "Msg Processed": "13/06/2021 10:23:59",
        "XML ID": "4445",
        "Total Lag": "1.3619476",
        "Create Lag": "0.8150592",
        "Process Lag": "0.5468884"
      }
    ]
  },
  {
    "stopID": "58",
    "stopQueryDate": "2021-06-13T09:24:01.231Z",
    "count": 0,
    "results": []
  },
  {
    "stopID": "37",
    "stopQueryDate": "2021-06-13T09:24:01.242Z",
    "count": 3,
    "results": [
      {
        "Direction": "Inbound",
        "Destination": "Broombridge",
        "Time": "00:05:31",
        "AVLS": "00:06:11",
        "Tram": "5019",
        "Action": "a",
        "Msg Sent": "13/06/2021 10:23:58",
        "Msg Received": "13/06/2021 10:23:58",
        "Msg Processed": "13/06/2021 10:23:59",
        "XML ID": "4445",
        "Total Lag": "1.3931807",
        "Create Lag": "0.8150592",
        "Process Lag": "0.5781215"
      },
      {
        "Direction": "Outbound",
        "Destination": "Bride's Glen",
        "Time": "00:03:14",
        "AVLS": "00:03:54",
        "Tram": "5010",
        "Action": "a",
        "Msg Sent": "13/06/2021 10:23:58",
        "Msg Received": "13/06/2021 10:23:58",
        "Msg Processed": "13/06/2021 10:23:59",
        "XML ID": "4445",
        "Total Lag": "1.2525606",
        "Create Lag": "0.8150592",
        "Process Lag": "0.4375014"
      },
      {
        "Direction": "Outbound",
        "Destination": "Bride's Glen",
        "Time": "00:17:02",
        "AVLS": "00:17:42",
        "Tram": "5018",
        "Action": "a",
        "Msg Sent": "13/06/2021 10:23:58",
        "Msg Received": "13/06/2021 10:23:58",
        "Msg Processed": "13/06/2021 10:23:59",
        "XML ID": "4445",
        "Total Lag": "1.377561",
        "Create Lag": "0.8150592",
        "Process Lag": "0.5625018"
      }
    ]
  },
  {
    "stopID": "38",
    "stopQueryDate": "2021-06-13T09:24:01.253Z",
    "count": 3,
    "results": [
      {
        "Direction": "Inbound",
        "Destination": "Broombridge",
        "Time": "00:04:01",
        "AVLS": "00:04:41",
        "Tram": "5019",
        "Action": "a",
        "Msg Sent": "13/06/2021 10:23:58",
        "Msg Received": "13/06/2021 10:23:58",
        "Msg Processed": "13/06/2021 10:23:59",
        "XML ID": "4445",
        "Total Lag": "1.3931807",
        "Create Lag": "0.8150592",
        "Process Lag": "0.5781215"
      },
      {
        "Direction": "Outbound",
        "Destination": "Bride's Glen",
        "Time": "00:04:42",
        "AVLS": "00:05:22",
        "Tram": "5010",
        "Action": "a",
        "Msg Sent": "13/06/2021 10:23:58",
        "Msg Received": "13/06/2021 10:23:58",
        "Msg Processed": "13/06/2021 10:23:59",
        "XML ID": "4445",
        "Total Lag": "1.2525606",
        "Create Lag": "0.8150592",
        "Process Lag": "0.4375014"
      },
      {
        "Direction": "Outbound",
        "Destination": "Bride's Glen",
        "Time": "00:18:30",
        "AVLS": "00:19:10",
        "Tram": "5018",
        "Action": "a",
        "Msg Sent": "13/06/2021 10:23:58",
        "Msg Received": "13/06/2021 10:23:58",
        "Msg Processed": "13/06/2021 10:23:59",
        "XML ID": "4445",
        "Total Lag": "1.377561",
        "Create Lag": "0.8150592",
        "Process Lag": "0.5625018"
      }
    ]
  },
  {
    "stopID": "43",
    "stopQueryDate": "2021-06-13T09:24:01.262Z",
    "count": 2,
    "results": [
      {
        "Direction": "Inbound",
        "Destination": "Broombridge",
        "Time": "00:12:36",
        "AVLS": "00:13:16",
        "Tram": "5028",
        "Action": "a",
        "Msg Sent": "13/06/2021 10:23:51",
        "Msg Received": "13/06/2021 10:23:51",
        "Msg Processed": "13/06/2021 10:23:51",
        "XML ID": "4442",
        "Total Lag": "0.7056875",
        "Create Lag": "0.6900629",
        "Process Lag": "0.0156246"
      },
      {
        "Direction": "Outbound",
        "Destination": "Bride's Glen",
        "Time": "00:11:36",
        "AVLS": "00:12:16",
        "Tram": "5010",
        "Action": "a",
        "Msg Sent": "13/06/2021 10:23:58",
        "Msg Received": "13/06/2021 10:23:58",
        "Msg Processed": "13/06/2021 10:23:59",
        "XML ID": "4445",
        "Total Lag": "1.2681848",
        "Create Lag": "0.8150592",
        "Process Lag": "0.4531256"
      }
    ]
  },
  {
    "stopID": "42",
    "stopQueryDate": "2021-06-13T09:24:01.289Z",
    "count": 2,
    "results": [
      {
        "Direction": "Inbound",
        "Destination": "Broombridge",
        "Time": "00:14:12",
        "AVLS": "00:14:52",
        "Tram": "5028",
        "Action": "a",
        "Msg Sent": "13/06/2021 10:23:51",
        "Msg Received": "13/06/2021 10:23:51",
        "Msg Processed": "13/06/2021 10:23:51",
        "XML ID": "4442",
        "Total Lag": "0.7213079",
        "Create Lag": "0.6900629",
        "Process Lag": "0.031245"
      },
      {
        "Direction": "Outbound",
        "Destination": "Bride's Glen",
        "Time": "00:10:03",
        "AVLS": "00:10:43",
        "Tram": "5010",
        "Action": "a",
        "Msg Sent": "13/06/2021 10:23:58",
        "Msg Received": "13/06/2021 10:23:58",
        "Msg Processed": "13/06/2021 10:23:59",
        "XML ID": "4445",
        "Total Lag": "1.2681848",
        "Create Lag": "0.8150592",
        "Process Lag": "0.4531256"
      }
    ]
  },
  {
    "stopID": "40",
    "stopQueryDate": "2021-06-13T09:24:01.297Z",
    "count": 3,
    "results": [
      {
        "Direction": "Inbound",
        "Destination": "Broombridge",
        "Time": "00:00:46",
        "AVLS": "00:01:26",
        "Tram": "5019",
        "Action": "a",
        "Msg Sent": "13/06/2021 10:23:58",
        "Msg Received": "13/06/2021 10:23:58",
        "Msg Processed": "13/06/2021 10:23:59",
        "XML ID": "4445",
        "Total Lag": "1.377561",
        "Create Lag": "0.8150592",
        "Process Lag": "0.5625018"
      },
      {
        "Direction": "Inbound",
        "Destination": "Broombridge",
        "Time": "00:16:23",
        "AVLS": "00:17:03",
        "Tram": "5028",
        "Action": "a",
        "Msg Sent": "13/06/2021 10:23:51",
        "Msg Received": "13/06/2021 10:23:51",
        "Msg Processed": "13/06/2021 10:23:51",
        "XML ID": "4442",
        "Total Lag": "0.7213079",
        "Create Lag": "0.6900629",
        "Process Lag": "0.031245"
      },
      {
        "Direction": "Outbound",
        "Destination": "Bride's Glen",
        "Time": "00:07:55",
        "AVLS": "00:08:35",
        "Tram": "5010",
        "Action": "a",
        "Msg Sent": "13/06/2021 10:23:58",
        "Msg Received": "13/06/2021 10:23:58",
        "Msg Processed": "13/06/2021 10:23:59",
        "XML ID": "4445",
        "Total Lag": "1.2525606",
        "Create Lag": "0.8150592",
        "Process Lag": "0.4375014"
      }
    ]
  },
  {
    "stopID": "45",
    "stopQueryDate": "2021-06-13T09:24:01.300Z",
    "count": 3,
    "results": [
      {
        "Direction": "Inbound",
        "Destination": "Broombridge",
        "Time": "00:10:03",
        "AVLS": "00:10:43",
        "Tram": "5028",
        "Action": "a",
        "Msg Sent": "13/06/2021 10:23:51",
        "Msg Received": "13/06/2021 10:23:51",
        "Msg Processed": "13/06/2021 10:23:51",
        "XML ID": "4442",
        "Total Lag": "0.7056875",
        "Create Lag": "0.6900629",
        "Process Lag": "0.0156246"
      },
      {
        "Direction": "Outbound",
        "Destination": "Bride's Glen",
        "Time": "00:01:24",
        "AVLS": "00:02:04",
        "Tram": "5035",
        "Action": "a",
        "Msg Sent": "13/06/2021 10:23:51",
        "Msg Received": "13/06/2021 10:23:51",
        "Msg Processed": "13/06/2021 10:23:51",
        "XML ID": "4442",
        "Total Lag": "0.7681794",
        "Create Lag": "0.6900629",
        "Process Lag": "0.0781165"
      },
      {
        "Direction": "Outbound",
        "Destination": "Bride's Glen",
        "Time": "00:14:09",
        "AVLS": "00:14:49",
        "Tram": "5010",
        "Action": "a",
        "Msg Sent": "13/06/2021 10:23:58",
        "Msg Received": "13/06/2021 10:23:58",
        "Msg Processed": "13/06/2021 10:23:59",
        "XML ID": "4445",
        "Total Lag": "1.2681848",
        "Create Lag": "0.8150592",
        "Process Lag": "0.4531256"
      }
    ]
  },
  {
    "stopID": "57",
    "stopQueryDate": "2021-06-13T09:24:01.307Z",
    "count": 1,
    "results": [
      {
        "Direction": "Outbound",
        "Destination": "Tallaght",
        "Time": "00:08:52",
        "AVLS": "00:09:32",
        "Tram": "3010",
        "Action": "d",
        "Msg Sent": "13/06/2021 10:23:58",
        "Msg Received": "13/06/2021 10:23:58",
        "Msg Processed": "13/06/2021 10:23:58",
        "XML ID": "4444",
        "Total Lag": "0.8931792",
        "Create Lag": "0.7525572",
        "Process Lag": "0.140622"
      }
    ]
  },
  {
    "stopID": "39",
    "stopQueryDate": "2021-06-13T09:24:01.316Z",
    "count": 3,
    "results": [
      {
        "Direction": "Inbound",
        "Destination": "Broombridge",
        "Time": "00:02:16",
        "AVLS": "00:02:56",
        "Tram": "5019",
        "Action": "a",
        "Msg Sent": "13/06/2021 10:23:58",
        "Msg Received": "13/06/2021 10:23:58",
        "Msg Processed": "13/06/2021 10:23:59",
        "XML ID": "4445",
        "Total Lag": "1.3931807",
        "Create Lag": "0.8150592",
        "Process Lag": "0.5781215"
      },
      {
        "Direction": "Inbound",
        "Destination": "Broombridge",
        "Time": "00:17:53",
        "AVLS": "00:18:33",
        "Tram": "5028",
        "Action": "a",
        "Msg Sent": "13/06/2021 10:23:51",
        "Msg Received": "13/06/2021 10:23:51",
        "Msg Processed": "13/06/2021 10:23:51",
        "XML ID": "4442",
        "Total Lag": "0.7213079",
        "Create Lag": "0.6900629",
        "Process Lag": "0.031245"
      },
      {
        "Direction": "Outbound",
        "Destination": "Bride's Glen",
        "Time": "00:06:27",
        "AVLS": "00:07:07",
        "Tram": "5010",
        "Action": "a",
        "Msg Sent": "13/06/2021 10:23:58",
        "Msg Received": "13/06/2021 10:23:58",
        "Msg Processed": "13/06/2021 10:23:59",
        "XML ID": "4445",
        "Total Lag": "1.2525606",
        "Create Lag": "0.8150592",
        "Process Lag": "0.4375014"
      }
    ]
  },
  {
    "stopID": "48",
    "stopQueryDate": "2021-06-13T09:24:01.325Z",
    "count": 2,
    "results": [
      {
        "Direction": "Inbound",
        "Destination": "Broombridge",
        "Time": "00:05:32",
        "AVLS": "00:06:12",
        "Tram": "5028",
        "Action": "d",
        "Msg Sent": "13/06/2021 10:23:51",
        "Msg Received": "13/06/2021 10:23:51",
        "Msg Processed": "13/06/2021 10:23:51",
        "XML ID": "4442",
        "Total Lag": "0.6900629",
        "Create Lag": "0.6900629",
        "Process Lag": "0"
      },
      {
        "Direction": "Inbound",
        "Destination": "Broombridge",
        "Time": "00:17:30",
        "AVLS": "00:18:10",
        "Tram": "5035",
        "Action": "d",
        "Msg Sent": "13/06/2021 10:23:51",
        "Msg Received": "13/06/2021 10:23:51",
        "Msg Processed": "13/06/2021 10:23:51",
        "XML ID": "4442",
        "Total Lag": "0.7838095",
        "Create Lag": "0.6900629",
        "Process Lag": "0.0937466"
      }
    ]
  },
  {
    "stopID": "56",
    "stopQueryDate": "2021-06-13T09:24:01.328Z",
    "count": 2,
    "results": [
      {
        "Direction": "Inbound",
        "Destination": "The Point",
        "Time": "00:13:33",
        "AVLS": "00:14:13",
        "Tram": "4012",
        "Action": "a",
        "Msg Sent": "13/06/2021 10:23:58",
        "Msg Received": "13/06/2021 10:23:58",
        "Msg Processed": "13/06/2021 10:23:59",
        "XML ID": "4445",
        "Total Lag": "1.1431816",
        "Create Lag": "0.8150592",
        "Process Lag": "0.3281224"
      },
      {
        "Direction": "Outbound",
        "Destination": "Tallaght",
        "Time": "00:09:31",
        "AVLS": "00:10:11",
        "Tram": "3010",
        "Action": "a",
        "Msg Sent": "13/06/2021 10:23:58",
        "Msg Received": "13/06/2021 10:23:58",
        "Msg Processed": "13/06/2021 10:23:58",
        "XML ID": "4444",
        "Total Lag": "0.8931792",
        "Create Lag": "0.7525572",
        "Process Lag": "0.140622"
      }
    ]
  },
  {
    "stopID": "46",
    "stopQueryDate": "2021-06-13T09:24:01.338Z",
    "count": 3,
    "results": [
      {
        "Direction": "Inbound",
        "Destination": "Broombridge",
        "Time": "00:08:41",
        "AVLS": "00:09:21",
        "Tram": "5028",
        "Action": "a",
        "Msg Sent": "13/06/2021 10:23:51",
        "Msg Received": "13/06/2021 10:23:51",
        "Msg Processed": "13/06/2021 10:23:51",
        "XML ID": "4442",
        "Total Lag": "0.7056875",
        "Create Lag": "0.6900629",
        "Process Lag": "0.0156246"
      },
      {
        "Direction": "Outbound",
        "Destination": "Bride's Glen",
        "Time": "00:02:47",
        "AVLS": "00:03:27",
        "Tram": "5035",
        "Action": "a",
        "Msg Sent": "13/06/2021 10:23:51",
        "Msg Received": "13/06/2021 10:23:51",
        "Msg Processed": "13/06/2021 10:23:51",
        "XML ID": "4442",
        "Total Lag": "0.7681794",
        "Create Lag": "0.6900629",
        "Process Lag": "0.0781165"
      },
      {
        "Direction": "Outbound",
        "Destination": "Bride's Glen",
        "Time": "00:15:32",
        "AVLS": "00:16:12",
        "Tram": "5010",
        "Action": "a",
        "Msg Sent": "13/06/2021 10:23:58",
        "Msg Received": "13/06/2021 10:23:58",
        "Msg Processed": "13/06/2021 10:23:59",
        "XML ID": "4445",
        "Total Lag": "1.2838166",
        "Create Lag": "0.8150592",
        "Process Lag": "0.4687574"
      }
    ]
  },
  {
    "stopID": "47",
    "stopQueryDate": "2021-06-13T09:24:01.346Z",
    "count": 4,
    "results": [
      {
        "Direction": "Inbound",
        "Destination": "Broombridge",
        "Time": "00:06:40",
        "AVLS": "00:07:20",
        "Tram": "5028",
        "Action": "a",
        "Msg Sent": "13/06/2021 10:23:51",
        "Msg Received": "13/06/2021 10:23:51",
        "Msg Processed": "13/06/2021 10:23:51",
        "XML ID": "4442",
        "Total Lag": "0.6900629",
        "Create Lag": "0.6900629",
        "Process Lag": "0"
      },
      {
        "Direction": "Inbound",
        "Destination": "Broombridge",
        "Time": "00:18:38",
        "AVLS": "00:19:18",
        "Tram": "5035",
        "Action": "a",
        "Msg Sent": "13/06/2021 10:23:51",
        "Msg Received": "13/06/2021 10:23:51",
        "Msg Processed": "13/06/2021 10:23:51",
        "XML ID": "4442",
        "Total Lag": "0.7838095",
        "Create Lag": "0.6900629",
        "Process Lag": "0.0937466"
      },
      {
        "Direction": "Outbound",
        "Destination": "Bride's Glen",
        "Time": "00:04:44",
        "AVLS": "00:05:24",
        "Tram": "5035",
        "Action": "a",
        "Msg Sent": "13/06/2021 10:23:51",
        "Msg Received": "13/06/2021 10:23:51",
        "Msg Processed": "13/06/2021 10:23:51",
        "XML ID": "4442",
        "Total Lag": "0.7681794",
        "Create Lag": "0.6900629",
        "Process Lag": "0.0781165"
      },
      {
        "Direction": "Outbound",
        "Destination": "Bride's Glen",
        "Time": "00:17:29",
        "AVLS": "00:18:09",
        "Tram": "5010",
        "Action": "a",
        "Msg Sent": "13/06/2021 10:23:58",
        "Msg Received": "13/06/2021 10:23:58",
        "Msg Processed": "13/06/2021 10:23:59",
        "XML ID": "4445",
        "Total Lag": "1.2838166",
        "Create Lag": "0.8150592",
        "Process Lag": "0.4687574"
      }
    ]
  },
  {
    "stopID": "49",
    "stopQueryDate": "2021-06-13T09:24:01.363Z",
    "count": 5,
    "results": [
      {
        "Direction": "Inbound",
        "Destination": "Belgard",
        "Time": "00:08:28",
        "AVLS": "00:09:08",
        "Tram": "3020",
        "Action": "a",
        "Msg Sent": "13/06/2021 10:23:58",
        "Msg Received": "13/06/2021 10:23:58",
        "Msg Processed": "13/06/2021 10:23:59",
        "XML ID": "4444",
        "Total Lag": "1.0027662",
        "Create Lag": "0.7525572",
        "Process Lag": "0.250209"
      },
      {
        "Direction": "Outbound",
        "Destination": "Saggart",
        "Time": "00:03:19",
        "AVLS": "00:03:59",
        "Tram": "3002",
        "Action": "a",
        "Msg Sent": "13/06/2021 10:23:58",
        "Msg Received": "13/06/2021 10:23:58",
        "Msg Processed": "13/06/2021 10:23:58",
        "XML ID": "4444",
        "Total Lag": "0.8306834",
        "Create Lag": "0.7525572",
        "Process Lag": "0.0781262"
      },
      {
        "Direction": "Outbound",
        "Destination": "Saggart",
        "Time": "00:10:19",
        "AVLS": "00:10:59",
        "Tram": "3019",
        "Action": "a",
        "Msg Sent": "13/06/2021 10:23:58",
        "Msg Received": "13/06/2021 10:23:58",
        "Msg Processed": "13/06/2021 10:23:58",
        "XML ID": "4444",
        "Total Lag": "0.9713116",
        "Create Lag": "0.7525572",
        "Process Lag": "0.2187544"
      },
      {
        "Direction": "Outbound",
        "Destination": "Saggart",
        "Time": "00:10:45",
        "AVLS": "00:11:25",
        "Tram": "3009",
        "Action": "a",
        "Msg Sent": "13/06/2021 10:23:58",
        "Msg Received": "13/06/2021 10:23:58",
        "Msg Processed": "13/06/2021 10:23:58",
        "XML ID": "4444",
        "Total Lag": "0.7872048",
        "Create Lag": "0.7525572",
        "Process Lag": "0.0346476"
      },
      {
        "Direction": "Outbound",
        "Destination": "Saggart",
        "Time": "00:10:45",
        "AVLS": "00:11:25",
        "Tram": "4004",
        "Action": "a",
        "Msg Sent": "13/06/2021 10:23:58",
        "Msg Received": "13/06/2021 10:23:58",
        "Msg Processed": "13/06/2021 10:23:58",
        "XML ID": "4444",
        "Total Lag": "0.8150592",
        "Create Lag": "0.7525572",
        "Process Lag": "0.062502"
      }
    ]
  },
  {
    "stopID": "54",
    "stopQueryDate": "2021-06-13T09:24:01.366Z",
    "count": 3,
    "results": [
      {
        "Direction": "Inbound",
        "Destination": "The Point",
        "Time": "00:10:38",
        "AVLS": "00:11:18",
        "Tram": "4012",
        "Action": "a",
        "Msg Sent": "13/06/2021 10:23:58",
        "Msg Received": "13/06/2021 10:23:58",
        "Msg Processed": "13/06/2021 10:23:59",
        "XML ID": "4445",
        "Total Lag": "1.1431816",
        "Create Lag": "0.8150592",
        "Process Lag": "0.3281224"
      },
      {
        "Direction": "Outbound",
        "Destination": "Tallaght",
        "Time": "00:01:38",
        "AVLS": "00:02:18",
        "Tram": "3005",
        "Action": "a",
        "Msg Sent": "13/06/2021 10:23:58",
        "Msg Received": "13/06/2021 10:23:58",
        "Msg Processed": "13/06/2021 10:23:58",
        "XML ID": "4444",
        "Total Lag": "0.8463055",
        "Create Lag": "0.7525572",
        "Process Lag": "0.0937483"
      },
      {
        "Direction": "Outbound",
        "Destination": "Tallaght",
        "Time": "00:12:58",
        "AVLS": "00:13:38",
        "Tram": "3010",
        "Action": "a",
        "Msg Sent": "13/06/2021 10:23:58",
        "Msg Received": "13/06/2021 10:23:58",
        "Msg Processed": "13/06/2021 10:23:58",
        "XML ID": "4444",
        "Total Lag": "0.9088068",
        "Create Lag": "0.7525572",
        "Process Lag": "0.1562496"
      }
    ]
  },
  {
    "stopID": "55",
    "stopQueryDate": "2021-06-13T09:24:01.375Z",
    "count": 3,
    "results": [
      {
        "Direction": "Inbound",
        "Destination": "The Point",
        "Time": "00:11:54",
        "AVLS": "00:12:34",
        "Tram": "4012",
        "Action": "a",
        "Msg Sent": "13/06/2021 10:23:58",
        "Msg Received": "13/06/2021 10:23:58",
        "Msg Processed": "13/06/2021 10:23:59",
        "XML ID": "4445",
        "Total Lag": "1.1431816",
        "Create Lag": "0.8150592",
        "Process Lag": "0.3281224"
      },
      {
        "Direction": "Outbound",
        "Destination": "Tallaght",
        "Time": "00:00:10",
        "AVLS": "00:00:50",
        "Tram": "3005",
        "Action": "a",
        "Msg Sent": "13/06/2021 10:23:58",
        "Msg Received": "13/06/2021 10:23:58",
        "Msg Processed": "13/06/2021 10:23:58",
        "XML ID": "4444",
        "Total Lag": "0.8463055",
        "Create Lag": "0.7525572",
        "Process Lag": "0.0937483"
      },
      {
        "Direction": "Outbound",
        "Destination": "Tallaght",
        "Time": "00:11:30",
        "AVLS": "00:12:10",
        "Tram": "3010",
        "Action": "a",
        "Msg Sent": "13/06/2021 10:23:58",
        "Msg Received": "13/06/2021 10:23:58",
        "Msg Processed": "13/06/2021 10:23:58",
        "XML ID": "4444",
        "Total Lag": "0.8931792",
        "Create Lag": "0.7525572",
        "Process Lag": "0.140622"
      }
    ]
  },
  {
    "stopID": "50",
    "stopQueryDate": "2021-06-13T09:24:01.385Z",
    "count": 6,
    "results": [
      {
        "Direction": "Inbound",
        "Destination": "Belgard",
        "Time": "00:06:40",
        "AVLS": "00:07:20",
        "Tram": "3020",
        "Action": "a",
        "Msg Sent": "13/06/2021 10:23:58",
        "Msg Received": "13/06/2021 10:23:58",
        "Msg Processed": "13/06/2021 10:23:59",
        "XML ID": "4444",
        "Total Lag": "1.0027662",
        "Create Lag": "0.7525572",
        "Process Lag": "0.250209"
      },
      {
        "Direction": "Inbound",
        "Destination": "Belgard",
        "Time": "00:17:40",
        "AVLS": "00:18:20",
        "Tram": "4010",
        "Action": "a",
        "Msg Sent": "13/06/2021 10:23:58",
        "Msg Received": "13/06/2021 10:23:58",
        "Msg Processed": "13/06/2021 10:23:59",
        "XML ID": "4445",
        "Total Lag": "1.0963068",
        "Create Lag": "0.8150592",
        "Process Lag": "0.2812476"
      },
      {
        "Direction": "Outbound",
        "Destination": "Saggart",
        "Time": "00:05:05",
        "AVLS": "00:05:45",
        "Tram": "3002",
        "Action": "a",
        "Msg Sent": "13/06/2021 10:23:58",
        "Msg Received": "13/06/2021 10:23:58",
        "Msg Processed": "13/06/2021 10:23:58",
        "XML ID": "4444",
        "Total Lag": "0.8306834",
        "Create Lag": "0.7525572",
        "Process Lag": "0.0781262"
      },
      {
        "Direction": "Outbound",
        "Destination": "Saggart",
        "Time": "00:12:05",
        "AVLS": "00:12:45",
        "Tram": "3019",
        "Action": "a",
        "Msg Sent": "13/06/2021 10:23:58",
        "Msg Received": "13/06/2021 10:23:58",
        "Msg Processed": "13/06/2021 10:23:58",
        "XML ID": "4444",
        "Total Lag": "0.9869304",
        "Create Lag": "0.7525572",
        "Process Lag": "0.2343732"
      },
      {
        "Direction": "Outbound",
        "Destination": "Saggart",
        "Time": "00:12:24",
        "AVLS": "00:13:04",
        "Tram": "3009",
        "Action": "a",
        "Msg Sent": "13/06/2021 10:23:58",
        "Msg Received": "13/06/2021 10:23:58",
        "Msg Processed": "13/06/2021 10:23:58",
        "XML ID": "4444",
        "Total Lag": "0.7994325",
        "Create Lag": "0.7525572",
        "Process Lag": "0.0468753"
      },
      {
        "Direction": "Outbound",
        "Destination": "Saggart",
        "Time": "00:12:24",
        "AVLS": "00:13:04",
        "Tram": "4004",
        "Action": "a",
        "Msg Sent": "13/06/2021 10:23:58",
        "Msg Received": "13/06/2021 10:23:58",
        "Msg Processed": "13/06/2021 10:23:58",
        "XML ID": "4444",
        "Total Lag": "0.8150592",
        "Create Lag": "0.7525572",
        "Process Lag": "0.062502"
      }
    ]
  },
  {
    "stopID": "51",
    "stopQueryDate": "2021-06-13T09:24:01.403Z",
    "count": 6,
    "results": [
      {
        "Direction": "Inbound",
        "Destination": "Belgard",
        "Time": "00:04:53",
        "AVLS": "00:05:33",
        "Tram": "3020",
        "Action": "a",
        "Msg Sent": "13/06/2021 10:23:58",
        "Msg Received": "13/06/2021 10:23:58",
        "Msg Processed": "13/06/2021 10:23:59",
        "XML ID": "4444",
        "Total Lag": "1.0027662",
        "Create Lag": "0.7525572",
        "Process Lag": "0.250209"
      },
      {
        "Direction": "Inbound",
        "Destination": "Belgard",
        "Time": "00:15:53",
        "AVLS": "00:16:33",
        "Tram": "4010",
        "Action": "a",
        "Msg Sent": "13/06/2021 10:23:58",
        "Msg Received": "13/06/2021 10:23:58",
        "Msg Processed": "13/06/2021 10:23:59",
        "XML ID": "4445",
        "Total Lag": "1.0963068",
        "Create Lag": "0.8150592",
        "Process Lag": "0.2812476"
      },
      {
        "Direction": "Outbound",
        "Destination": "Saggart",
        "Time": "00:06:52",
        "AVLS": "00:07:32",
        "Tram": "3002",
        "Action": "a",
        "Msg Sent": "13/06/2021 10:23:58",
        "Msg Received": "13/06/2021 10:23:58",
        "Msg Processed": "13/06/2021 10:23:58",
        "XML ID": "4444",
        "Total Lag": "0.8306834",
        "Create Lag": "0.7525572",
        "Process Lag": "0.0781262"
      },
      {
        "Direction": "Outbound",
        "Destination": "Saggart",
        "Time": "00:13:52",
        "AVLS": "00:14:32",
        "Tram": "3019",
        "Action": "a",
        "Msg Sent": "13/06/2021 10:23:58",
        "Msg Received": "13/06/2021 10:23:58",
        "Msg Processed": "13/06/2021 10:23:58",
        "XML ID": "4444",
        "Total Lag": "0.9869304",
        "Create Lag": "0.7525572",
        "Process Lag": "0.2343732"
      },
      {
        "Direction": "Outbound",
        "Destination": "Saggart",
        "Time": "00:14:04",
        "AVLS": "00:14:44",
        "Tram": "3009",
        "Action": "a",
        "Msg Sent": "13/06/2021 10:23:58",
        "Msg Received": "13/06/2021 10:23:58",
        "Msg Processed": "13/06/2021 10:23:58",
        "XML ID": "4444",
        "Total Lag": "0.7994325",
        "Create Lag": "0.7525572",
        "Process Lag": "0.0468753"
      },
      {
        "Direction": "Outbound",
        "Destination": "Saggart",
        "Time": "00:14:04",
        "AVLS": "00:14:44",
        "Tram": "4004",
        "Action": "a",
        "Msg Sent": "13/06/2021 10:23:58",
        "Msg Received": "13/06/2021 10:23:58",
        "Msg Processed": "13/06/2021 10:23:58",
        "XML ID": "4444",
        "Total Lag": "0.8150592",
        "Create Lag": "0.7525572",
        "Process Lag": "0.062502"
      }
    ]
  },
  {
    "stopID": "1",
    "stopQueryDate": "2021-06-13T09:24:01.413Z",
    "count": 4,
    "results": [
      {
        "Direction": "Inbound",
        "Destination": "The Point",
        "Time": "00:02:20",
        "AVLS": "00:03:00",
        "Tram": "3008",
        "Action": "d",
        "Msg Sent": "13/06/2021 10:23:58",
        "Msg Received": "13/06/2021 10:23:58",
        "Msg Processed": "13/06/2021 10:23:58",
        "XML ID": "4444",
        "Total Lag": "0.8775555",
        "Create Lag": "0.7525572",
        "Process Lag": "0.1249983"
      },
      {
        "Direction": "Inbound",
        "Destination": "The Point",
        "Time": "00:09:22",
        "AVLS": "00:10:02",
        "Tram": "3011",
        "Action": "d",
        "Msg Sent": "13/06/2021 10:23:58",
        "Msg Received": "13/06/2021 10:23:58",
        "Msg Processed": "13/06/2021 10:23:58",
        "XML ID": "4444",
        "Total Lag": "0.9244321",
        "Create Lag": "0.7525572",
        "Process Lag": "0.1718749"
      },
      {
        "Direction": "Terminating",
        "Destination": "Tallaght",
        "Time": "00:02:25",
        "AVLS": "00:03:05",
        "Tram": "3011",
        "Action": "a",
        "Msg Sent": "13/06/2021 10:23:58",
        "Msg Received": "13/06/2021 10:23:58",
        "Msg Processed": "13/06/2021 10:23:58",
        "XML ID": "4444",
        "Total Lag": "0.9244321",
        "Create Lag": "0.7525572",
        "Process Lag": "0.1718749"
      },
      {
        "Direction": "Terminating",
        "Destination": "Tallaght",
        "Time": "00:09:49",
        "AVLS": "00:10:29",
        "Tram": "4011",
        "Action": "a",
        "Msg Sent": "13/06/2021 10:23:58",
        "Msg Received": "13/06/2021 10:23:58",
        "Msg Processed": "13/06/2021 10:23:59",
        "XML ID": "4445",
        "Total Lag": "1.1276831",
        "Create Lag": "0.8150592",
        "Process Lag": "0.3126239"
      }
    ]
  },
  {
    "stopID": "27",
    "stopQueryDate": "2021-06-13T09:24:01.421Z",
    "count": 3,
    "results": [
      {
        "Direction": "Inbound",
        "Destination": "Broombridge",
        "Time": "00:10:40",
        "AVLS": "00:11:20",
        "Tram": "5024",
        "Action": "a",
        "Msg Sent": "13/06/2021 10:23:48",
        "Msg Received": "13/06/2021 10:23:48",
        "Msg Processed": "13/06/2021 10:23:49",
        "XML ID": "4441",
        "Total Lag": "1.3150639",
        "Create Lag": "0.7507327",
        "Process Lag": "0.5643312"
      },
      {
        "Direction": "Outbound",
        "Destination": "Bride's Glen",
        "Time": "00:00:00",
        "AVLS": "00:00:15",
        "Tram": "5018",
        "Action": "a",
        "Msg Sent": "13/06/2021 10:23:58",
        "Msg Received": "13/06/2021 10:23:58",
        "Msg Processed": "13/06/2021 10:23:59",
        "XML ID": "4445",
        "Total Lag": "1.3463073",
        "Create Lag": "0.8150592",
        "Process Lag": "0.5312481"
      },
      {
        "Direction": "Outbound",
        "Destination": "Bride's Glen",
        "Time": "00:15:56",
        "AVLS": "00:16:36",
        "Tram": "5004",
        "Action": "a",
        "Msg Sent": "13/06/2021 10:23:58",
        "Msg Received": "13/06/2021 10:23:58",
        "Msg Processed": "13/06/2021 10:23:59",
        "XML ID": "4445",
        "Total Lag": "1.2213151",
        "Create Lag": "0.8150592",
        "Process Lag": "0.4062559"
      }
    ]
  },
  {
    "stopID": "31",
    "stopQueryDate": "2021-06-13T09:24:01.424Z",
    "count": 3,
    "results": [
      {
        "Direction": "Inbound",
        "Destination": "Broombridge",
        "Time": "00:04:08",
        "AVLS": "00:04:48",
        "Tram": "5024",
        "Action": "a",
        "Msg Sent": "13/06/2021 10:23:48",
        "Msg Received": "13/06/2021 10:23:48",
        "Msg Processed": "13/06/2021 10:23:49",
        "XML ID": "4441",
        "Total Lag": "1.2994307",
        "Create Lag": "0.7507327",
        "Process Lag": "0.548698"
      },
      {
        "Direction": "Inbound",
        "Destination": "Broombridge",
        "Time": "00:16:54",
        "AVLS": "00:17:34",
        "Tram": "5019",
        "Action": "a",
        "Msg Sent": "13/06/2021 10:23:58",
        "Msg Received": "13/06/2021 10:23:58",
        "Msg Processed": "13/06/2021 10:23:59",
        "XML ID": "4445",
        "Total Lag": "1.4088067",
        "Create Lag": "0.8150592",
        "Process Lag": "0.5937475"
      },
      {
        "Direction": "Outbound",
        "Destination": "Bride's Glen",
        "Time": "00:06:31",
        "AVLS": "00:07:11",
        "Tram": "5018",
        "Action": "a",
        "Msg Sent": "13/06/2021 10:23:58",
        "Msg Received": "13/06/2021 10:23:58",
        "Msg Processed": "13/06/2021 10:23:59",
        "XML ID": "4445",
        "Total Lag": "1.3619476",
        "Create Lag": "0.8150592",
        "Process Lag": "0.5468884"
      }
    ]
  },
  {
    "stopID": "44",
    "stopQueryDate": "2021-06-13T09:24:01.439Z",
    "count": 3,
    "results": [
      {
        "Direction": "Inbound",
        "Destination": "Broombridge",
        "Time": "00:11:32",
        "AVLS": "00:12:12",
        "Tram": "5028",
        "Action": "a",
        "Msg Sent": "13/06/2021 10:23:51",
        "Msg Received": "13/06/2021 10:23:51",
        "Msg Processed": "13/06/2021 10:23:51",
        "XML ID": "4442",
        "Total Lag": "0.7056875",
        "Create Lag": "0.6900629",
        "Process Lag": "0.0156246"
      },
      {
        "Direction": "Outbound",
        "Destination": "Bride's Glen",
        "Time": "00:00:00",
        "AVLS": "00:00:36",
        "Tram": "5035",
        "Action": "a",
        "Msg Sent": "13/06/2021 10:23:51",
        "Msg Received": "13/06/2021 10:23:51",
        "Msg Processed": "13/06/2021 10:23:51",
        "XML ID": "4442",
        "Total Lag": "0.7681794",
        "Create Lag": "0.6900629",
        "Process Lag": "0.0781165"
      },
      {
        "Direction": "Outbound",
        "Destination": "Bride's Glen",
        "Time": "00:12:41",
        "AVLS": "00:13:21",
        "Tram": "5010",
        "Action": "a",
        "Msg Sent": "13/06/2021 10:23:58",
        "Msg Received": "13/06/2021 10:23:58",
        "Msg Processed": "13/06/2021 10:23:59",
        "XML ID": "4445",
        "Total Lag": "1.2681848",
        "Create Lag": "0.8150592",
        "Process Lag": "0.4531256"
      }
    ]
  },
  {
    "stopID": "52",
    "stopQueryDate": "2021-06-13T09:24:01.443Z",
    "count": 7,
    "results": [
      {
        "Direction": "Inbound",
        "Destination": "Belgard",
        "Time": "00:03:37",
        "AVLS": "00:04:17",
        "Tram": "3020",
        "Action": "a",
        "Msg Sent": "13/06/2021 10:23:58",
        "Msg Received": "13/06/2021 10:23:58",
        "Msg Processed": "13/06/2021 10:23:59",
        "XML ID": "4444",
        "Total Lag": "1.0027662",
        "Create Lag": "0.7525572",
        "Process Lag": "0.250209"
      },
      {
        "Direction": "Inbound",
        "Destination": "Belgard",
        "Time": "00:14:37",
        "AVLS": "00:15:17",
        "Tram": "4010",
        "Action": "a",
        "Msg Sent": "13/06/2021 10:23:58",
        "Msg Received": "13/06/2021 10:23:58",
        "Msg Processed": "13/06/2021 10:23:59",
        "XML ID": "4445",
        "Total Lag": "1.0963068",
        "Create Lag": "0.8150592",
        "Process Lag": "0.2812476"
      },
      {
        "Direction": "Outbound",
        "Destination": "Saggart",
        "Time": "00:00:00",
        "AVLS": "00:00:00",
        "Tram": "4010",
        "Action": "a",
        "Msg Sent": "13/06/2021 10:23:58",
        "Msg Received": "13/06/2021 10:23:58",
        "Msg Processed": "13/06/2021 10:23:59",
        "XML ID": "4445",
        "Total Lag": "1.0806815",
        "Create Lag": "0.8150592",
        "Process Lag": "0.2656223"
      },
      {
        "Direction": "Outbound",
        "Destination": "Saggart",
        "Time": "00:08:09",
        "AVLS": "00:08:49",
        "Tram": "3002",
        "Action": "a",
        "Msg Sent": "13/06/2021 10:23:58",
        "Msg Received": "13/06/2021 10:23:58",
        "Msg Processed": "13/06/2021 10:23:58",
        "XML ID": "4444",
        "Total Lag": "0.8463055",
        "Create Lag": "0.7525572",
        "Process Lag": "0.0937483"
      },
      {
        "Direction": "Outbound",
        "Destination": "Saggart",
        "Time": "00:15:09",
        "AVLS": "00:15:49",
        "Tram": "3019",
        "Action": "a",
        "Msg Sent": "13/06/2021 10:23:58",
        "Msg Received": "13/06/2021 10:23:58",
        "Msg Processed": "13/06/2021 10:23:58",
        "XML ID": "4444",
        "Total Lag": "0.9869304",
        "Create Lag": "0.7525572",
        "Process Lag": "0.2343732"
      },
      {
        "Direction": "Outbound",
        "Destination": "Saggart",
        "Time": "00:15:16",
        "AVLS": "00:15:56",
        "Tram": "3009",
        "Action": "a",
        "Msg Sent": "13/06/2021 10:23:58",
        "Msg Received": "13/06/2021 10:23:58",
        "Msg Processed": "13/06/2021 10:23:58",
        "XML ID": "4444",
        "Total Lag": "0.7994325",
        "Create Lag": "0.7525572",
        "Process Lag": "0.0468753"
      },
      {
        "Direction": "Outbound",
        "Destination": "Saggart",
        "Time": "00:15:16",
        "AVLS": "00:15:56",
        "Tram": "4004",
        "Action": "a",
        "Msg Sent": "13/06/2021 10:23:58",
        "Msg Received": "13/06/2021 10:23:58",
        "Msg Processed": "13/06/2021 10:23:58",
        "XML ID": "4444",
        "Total Lag": "0.8306834",
        "Create Lag": "0.7525572",
        "Process Lag": "0.0781262"
      }
    ]
  },
  {
    "stopID": "53",
    "stopQueryDate": "2021-06-13T09:24:01.461Z",
    "count": 7,
    "results": [
      {
        "Direction": "Inbound",
        "Destination": "Belgard",
        "Time": "00:01:22",
        "AVLS": "00:02:02",
        "Tram": "3020",
        "Action": "d",
        "Msg Sent": "13/06/2021 10:23:58",
        "Msg Received": "13/06/2021 10:23:58",
        "Msg Processed": "13/06/2021 10:23:58",
        "XML ID": "4444",
        "Total Lag": "0.9869304",
        "Create Lag": "0.7525572",
        "Process Lag": "0.2343732"
      },
      {
        "Direction": "Inbound",
        "Destination": "Belgard",
        "Time": "00:12:22",
        "AVLS": "00:13:02",
        "Tram": "4010",
        "Action": "d",
        "Msg Sent": "13/06/2021 10:23:58",
        "Msg Received": "13/06/2021 10:23:58",
        "Msg Processed": "13/06/2021 10:23:59",
        "XML ID": "4445",
        "Total Lag": "1.0963068",
        "Create Lag": "0.8150592",
        "Process Lag": "0.2812476"
      },
      {
        "Direction": "Terminating",
        "Destination": "Saggart",
        "Time": "00:01:33",
        "AVLS": "00:02:13",
        "Tram": "4010",
        "Action": "a",
        "Msg Sent": "13/06/2021 10:23:58",
        "Msg Received": "13/06/2021 10:23:58",
        "Msg Processed": "13/06/2021 10:23:59",
        "XML ID": "4445",
        "Total Lag": "1.0806815",
        "Create Lag": "0.8150592",
        "Process Lag": "0.2656223"
      },
      {
        "Direction": "Terminating",
        "Destination": "Saggart",
        "Time": "00:10:22",
        "AVLS": "00:11:02",
        "Tram": "3002",
        "Action": "a",
        "Msg Sent": "13/06/2021 10:23:58",
        "Msg Received": "13/06/2021 10:23:58",
        "Msg Processed": "13/06/2021 10:23:58",
        "XML ID": "4444",
        "Total Lag": "0.8463055",
        "Create Lag": "0.7525572",
        "Process Lag": "0.0937483"
      },
      {
        "Direction": "Terminating",
        "Destination": "Saggart",
        "Time": "00:17:20",
        "AVLS": "00:18:00",
        "Tram": "3009",
        "Action": "a",
        "Msg Sent": "13/06/2021 10:23:58",
        "Msg Received": "13/06/2021 10:23:58",
        "Msg Processed": "13/06/2021 10:23:58",
        "XML ID": "4444",
        "Total Lag": "0.7994325",
        "Create Lag": "0.7525572",
        "Process Lag": "0.0468753"
      },
      {
        "Direction": "Terminating",
        "Destination": "Saggart",
        "Time": "00:17:20",
        "AVLS": "00:18:00",
        "Tram": "4004",
        "Action": "a",
        "Msg Sent": "13/06/2021 10:23:58",
        "Msg Received": "13/06/2021 10:23:58",
        "Msg Processed": "13/06/2021 10:23:58",
        "XML ID": "4444",
        "Total Lag": "0.8306834",
        "Create Lag": "0.7525572",
        "Process Lag": "0.0781262"
      },
      {
        "Direction": "Terminating",
        "Destination": "Saggart",
        "Time": "00:17:22",
        "AVLS": "00:18:02",
        "Tram": "3019",
        "Action": "a",
        "Msg Sent": "13/06/2021 10:23:58",
        "Msg Received": "13/06/2021 10:23:58",
        "Msg Processed": "13/06/2021 10:23:58",
        "XML ID": "4444",
        "Total Lag": "0.9869304",
        "Create Lag": "0.7525572",
        "Process Lag": "0.2343732"
      }
    ]
  }
]